[
  {
    "State Postal": "MN",
    "FIPS Code": 0,
    "County Name": "Minnesota",
    "TOTAL VOTES CAST": 2928942,
    "FirstOne": "Barack",
    "LastOne": "Obama",
    "VotesOne": 1547668,
    "IdOne": 1918,
    "FirstTwo": "Mitt",
    "LastTwo": "Romney",
    "VotesTwo": 1321575,
    "IdTwo": 893,
    "FirstThree": "Rocky",
    "LastThree": "Anderson",
    "VotesThree": 2013,
    "IDThree": 43773,
    "FirstFour": "Jim",
    "LastFour": "Carlson",
    "VotesFour": 3172,
    "IdFour": 62588,
    "FirstFive": "Virgil",
    "LastFive": "Goode",
    "VotesFive": 3727,
    "IDFive": 713,
    "FirstSix": "James",
    "LastSix": "Harris",
    "VotesSix": 1062,
    "IDSix": 3486,
    "FirstSeven": "Gary",
    "LastSeven": "Johnson",
    "VotesSeven": 35158,
    "IDSeven": 31708,
    "FirstEight": "Peta",
    "LastEight": "Lindsay",
    "VotesEight": 416,
    "IDEight": 62562,
    "FirstNine": "Jill",
    "LastNine": "Stein",
    "VotesNine": 13045,
    "IdNine": 895,
    "": 2928942
  },
  {
    "State Postal": "MN",
    "FIPS Code": 27001,
    "County Name": "Aitkin",
    "TOTAL VOTES CAST": 9109,
    "FirstOne": "Barack",
    "LastOne": "Obama",
    "VotesOne": 4412,
    "IdOne": 1918,
    "FirstTwo": "Mitt",
    "LastTwo": "Romney",
    "VotesTwo": 4533,
    "IdTwo": 893,
    "FirstThree": "Rocky",
    "LastThree": "Anderson",
    "VotesThree": 9,
    "IDThree": 43773,
    "FirstFour": "Jim",
    "LastFour": "Carlson",
    "VotesFour": 22,
    "IdFour": 62588,
    "FirstFive": "Virgil",
    "LastFive": "Goode",
    "VotesFive": 9,
    "IDFive": 713,
    "FirstSix": "James",
    "LastSix": "Harris",
    "VotesSix": 6,
    "IDSix": 3486,
    "FirstSeven": "Gary",
    "LastSeven": "Johnson",
    "VotesSeven": 80,
    "IDSeven": 31708,
    "FirstEight": "Peta",
    "LastEight": "Lindsay",
    "VotesEight": 0,
    "IDEight": 62562,
    "FirstNine": "Jill",
    "LastNine": "Stein",
    "VotesNine": 33,
    "IdNine": 895,
    "": 9109
  },
  {
    "State Postal": "MN",
    "FIPS Code": 27003,
    "County Name": "Anoka",
    "TOTAL VOTES CAST": 185714,
    "FirstOne": "Barack",
    "LastOne": "Obama",
    "VotesOne": 88611,
    "IdOne": 1918,
    "FirstTwo": "Mitt",
    "LastTwo": "Romney",
    "VotesTwo": 93430,
    "IdTwo": 893,
    "FirstThree": "Rocky",
    "LastThree": "Anderson",
    "VotesThree": 122,
    "IDThree": 43773,
    "FirstFour": "Jim",
    "LastFour": "Carlson",
    "VotesFour": 207,
    "IdFour": 62588,
    "FirstFive": "Virgil",
    "LastFive": "Goode",
    "VotesFive": 232,
    "IDFive": 713,
    "FirstSix": "James",
    "LastSix": "Harris",
    "VotesSix": 48,
    "IDSix": 3486,
    "FirstSeven": "Gary",
    "LastSeven": "Johnson",
    "VotesSeven": 2284,
    "IDSeven": 31708,
    "FirstEight": "Peta",
    "LastEight": "Lindsay",
    "VotesEight": 17,
    "IDEight": 62562,
    "FirstNine": "Jill",
    "LastNine": "Stein",
    "VotesNine": 687,
    "IdNine": 895,
    "": 185714
  },
  {
    "State Postal": "MN",
    "FIPS Code": 27005,
    "County Name": "Becker",
    "TOTAL VOTES CAST": 16329,
    "FirstOne": "Barack",
    "LastOne": "Obama",
    "VotesOne": 6829,
    "IdOne": 1918,
    "FirstTwo": "Mitt",
    "LastTwo": "Romney",
    "VotesTwo": 9204,
    "IdTwo": 893,
    "FirstThree": "Rocky",
    "LastThree": "Anderson",
    "VotesThree": 15,
    "IDThree": 43773,
    "FirstFour": "Jim",
    "LastFour": "Carlson",
    "VotesFour": 26,
    "IdFour": 62588,
    "FirstFive": "Virgil",
    "LastFive": "Goode",
    "VotesFive": 25,
    "IDFive": 713,
    "FirstSix": "James",
    "LastSix": "Harris",
    "VotesSix": 6,
    "IDSix": 3486,
    "FirstSeven": "Gary",
    "LastSeven": "Johnson",
    "VotesSeven": 155,
    "IDSeven": 31708,
    "FirstEight": "Peta",
    "LastEight": "Lindsay",
    "VotesEight": 3,
    "IDEight": 62562,
    "FirstNine": "Jill",
    "LastNine": "Stein",
    "VotesNine": 57,
    "IdNine": 895,
    "": 16329
  },
  {
    "State Postal": "MN",
    "FIPS Code": 27007,
    "County Name": "Beltrami",
    "TOTAL VOTES CAST": 21949,
    "FirstOne": "Barack",
    "LastOne": "Obama",
    "VotesOne": 11818,
    "IdOne": 1918,
    "FirstTwo": "Mitt",
    "LastTwo": "Romney",
    "VotesTwo": 9637,
    "IdTwo": 893,
    "FirstThree": "Rocky",
    "LastThree": "Anderson",
    "VotesThree": 14,
    "IDThree": 43773,
    "FirstFour": "Jim",
    "LastFour": "Carlson",
    "VotesFour": 32,
    "IdFour": 62588,
    "FirstFive": "Virgil",
    "LastFive": "Goode",
    "VotesFive": 38,
    "IDFive": 713,
    "FirstSix": "James",
    "LastSix": "Harris",
    "VotesSix": 12,
    "IDSix": 3486,
    "FirstSeven": "Gary",
    "LastSeven": "Johnson",
    "VotesSeven": 268,
    "IDSeven": 31708,
    "FirstEight": "Peta",
    "LastEight": "Lindsay",
    "VotesEight": 3,
    "IDEight": 62562,
    "FirstNine": "Jill",
    "LastNine": "Stein",
    "VotesNine": 121,
    "IdNine": 895,
    "": 21949
  },
  {
    "State Postal": "MN",
    "FIPS Code": 27009,
    "County Name": "Benton",
    "TOTAL VOTES CAST": 19521,
    "FirstOne": "Barack",
    "LastOne": "Obama",
    "VotesOne": 8173,
    "IdOne": 1918,
    "FirstTwo": "Mitt",
    "LastTwo": "Romney",
    "VotesTwo": 10849,
    "IdTwo": 893,
    "FirstThree": "Rocky",
    "LastThree": "Anderson",
    "VotesThree": 12,
    "IDThree": 43773,
    "FirstFour": "Jim",
    "LastFour": "Carlson",
    "VotesFour": 28,
    "IdFour": 62588,
    "FirstFive": "Virgil",
    "LastFive": "Goode",
    "VotesFive": 40,
    "IDFive": 713,
    "FirstSix": "James",
    "LastSix": "Harris",
    "VotesSix": 8,
    "IDSix": 3486,
    "FirstSeven": "Gary",
    "LastSeven": "Johnson",
    "VotesSeven": 296,
    "IDSeven": 31708,
    "FirstEight": "Peta",
    "LastEight": "Lindsay",
    "VotesEight": 4,
    "IDEight": 62562,
    "FirstNine": "Jill",
    "LastNine": "Stein",
    "VotesNine": 96,
    "IdNine": 895,
    "": 19521
  },
  {
    "State Postal": "MN",
    "FIPS Code": 27011,
    "County Name": "Big Stone",
    "TOTAL VOTES CAST": 2783,
    "FirstOne": "Barack",
    "LastOne": "Obama",
    "VotesOne": 1345,
    "IdOne": 1918,
    "FirstTwo": "Mitt",
    "LastTwo": "Romney",
    "VotesTwo": 1385,
    "IdTwo": 893,
    "FirstThree": "Rocky",
    "LastThree": "Anderson",
    "VotesThree": 2,
    "IDThree": 43773,
    "FirstFour": "Jim",
    "LastFour": "Carlson",
    "VotesFour": 7,
    "IdFour": 62588,
    "FirstFive": "Virgil",
    "LastFive": "Goode",
    "VotesFive": 4,
    "IDFive": 713,
    "FirstSix": "James",
    "LastSix": "Harris",
    "VotesSix": 2,
    "IDSix": 3486,
    "FirstSeven": "Gary",
    "LastSeven": "Johnson",
    "VotesSeven": 29,
    "IDSeven": 31708,
    "FirstEight": "Peta",
    "LastEight": "Lindsay",
    "VotesEight": 0,
    "IDEight": 62562,
    "FirstNine": "Jill",
    "LastNine": "Stein",
    "VotesNine": 8,
    "IdNine": 895,
    "": 2783
  },
  {
    "State Postal": "MN",
    "FIPS Code": 27013,
    "County Name": "Blue Earth",
    "TOTAL VOTES CAST": 34039,
    "FirstOne": "Barack",
    "LastOne": "Obama",
    "VotesOne": 18164,
    "IdOne": 1918,
    "FirstTwo": "Mitt",
    "LastTwo": "Romney",
    "VotesTwo": 14916,
    "IdTwo": 893,
    "FirstThree": "Rocky",
    "LastThree": "Anderson",
    "VotesThree": 23,
    "IDThree": 43773,
    "FirstFour": "Jim",
    "LastFour": "Carlson",
    "VotesFour": 46,
    "IdFour": 62588,
    "FirstFive": "Virgil",
    "LastFive": "Goode",
    "VotesFive": 61,
    "IDFive": 713,
    "FirstSix": "James",
    "LastSix": "Harris",
    "VotesSix": 12,
    "IDSix": 3486,
    "FirstSeven": "Gary",
    "LastSeven": "Johnson",
    "VotesSeven": 572,
    "IDSeven": 31708,
    "FirstEight": "Peta",
    "LastEight": "Lindsay",
    "VotesEight": 5,
    "IDEight": 62562,
    "FirstNine": "Jill",
    "LastNine": "Stein",
    "VotesNine": 222,
    "IdNine": 895,
    "": 34039
  },
  {
    "State Postal": "MN",
    "FIPS Code": 27015,
    "County Name": "Brown",
    "TOTAL VOTES CAST": 13882,
    "FirstOne": "Barack",
    "LastOne": "Obama",
    "VotesOne": 5630,
    "IdOne": 1918,
    "FirstTwo": "Mitt",
    "LastTwo": "Romney",
    "VotesTwo": 7938,
    "IdTwo": 893,
    "FirstThree": "Rocky",
    "LastThree": "Anderson",
    "VotesThree": 8,
    "IDThree": 43773,
    "FirstFour": "Jim",
    "LastFour": "Carlson",
    "VotesFour": 24,
    "IdFour": 62588,
    "FirstFive": "Virgil",
    "LastFive": "Goode",
    "VotesFive": 24,
    "IDFive": 713,
    "FirstSix": "James",
    "LastSix": "Harris",
    "VotesSix": 7,
    "IDSix": 3486,
    "FirstSeven": "Gary",
    "LastSeven": "Johnson",
    "VotesSeven": 198,
    "IDSeven": 31708,
    "FirstEight": "Peta",
    "LastEight": "Lindsay",
    "VotesEight": 3,
    "IDEight": 62562,
    "FirstNine": "Jill",
    "LastNine": "Stein",
    "VotesNine": 44,
    "IdNine": 895,
    "": 13882
  },
  {
    "State Postal": "MN",
    "FIPS Code": 27017,
    "County Name": "Carlton",
    "TOTAL VOTES CAST": 18356,
    "FirstOne": "Barack",
    "LastOne": "Obama",
    "VotesOne": 11389,
    "IdOne": 1918,
    "FirstTwo": "Mitt",
    "LastTwo": "Romney",
    "VotesTwo": 6586,
    "IdTwo": 893,
    "FirstThree": "Rocky",
    "LastThree": "Anderson",
    "VotesThree": 15,
    "IDThree": 43773,
    "FirstFour": "Jim",
    "LastFour": "Carlson",
    "VotesFour": 29,
    "IdFour": 62588,
    "FirstFive": "Virgil",
    "LastFive": "Goode",
    "VotesFive": 54,
    "IDFive": 713,
    "FirstSix": "James",
    "LastSix": "Harris",
    "VotesSix": 12,
    "IDSix": 3486,
    "FirstSeven": "Gary",
    "LastSeven": "Johnson",
    "VotesSeven": 178,
    "IDSeven": 31708,
    "FirstEight": "Peta",
    "LastEight": "Lindsay",
    "VotesEight": 1,
    "IDEight": 62562,
    "FirstNine": "Jill",
    "LastNine": "Stein",
    "VotesNine": 83,
    "IdNine": 895,
    "": 18356
  },
  {
    "State Postal": "MN",
    "FIPS Code": 27019,
    "County Name": "Carver",
    "TOTAL VOTES CAST": 52747,
    "FirstOne": "Barack",
    "LastOne": "Obama",
    "VotesOne": 20745,
    "IdOne": 1918,
    "FirstTwo": "Mitt",
    "LastTwo": "Romney",
    "VotesTwo": 31155,
    "IdTwo": 893,
    "FirstThree": "Rocky",
    "LastThree": "Anderson",
    "VotesThree": 25,
    "IDThree": 43773,
    "FirstFour": "Jim",
    "LastFour": "Carlson",
    "VotesFour": 35,
    "IdFour": 62588,
    "FirstFive": "Virgil",
    "LastFive": "Goode",
    "VotesFive": 42,
    "IDFive": 713,
    "FirstSix": "James",
    "LastSix": "Harris",
    "VotesSix": 7,
    "IDSix": 3486,
    "FirstSeven": "Gary",
    "LastSeven": "Johnson",
    "VotesSeven": 555,
    "IDSeven": 31708,
    "FirstEight": "Peta",
    "LastEight": "Lindsay",
    "VotesEight": 7,
    "IDEight": 62562,
    "FirstNine": "Jill",
    "LastNine": "Stein",
    "VotesNine": 164,
    "IdNine": 895,
    "": 52747
  },
  {
    "State Postal": "MN",
    "FIPS Code": 27021,
    "County Name": "Cass",
    "TOTAL VOTES CAST": 16080,
    "FirstOne": "Barack",
    "LastOne": "Obama",
    "VotesOne": 6858,
    "IdOne": 1918,
    "FirstTwo": "Mitt",
    "LastTwo": "Romney",
    "VotesTwo": 8957,
    "IdTwo": 893,
    "FirstThree": "Rocky",
    "LastThree": "Anderson",
    "VotesThree": 12,
    "IDThree": 43773,
    "FirstFour": "Jim",
    "LastFour": "Carlson",
    "VotesFour": 32,
    "IdFour": 62588,
    "FirstFive": "Virgil",
    "LastFive": "Goode",
    "VotesFive": 27,
    "IDFive": 713,
    "FirstSix": "James",
    "LastSix": "Harris",
    "VotesSix": 5,
    "IDSix": 3486,
    "FirstSeven": "Gary",
    "LastSeven": "Johnson",
    "VotesSeven": 116,
    "IDSeven": 31708,
    "FirstEight": "Peta",
    "LastEight": "Lindsay",
    "VotesEight": 4,
    "IDEight": 62562,
    "FirstNine": "Jill",
    "LastNine": "Stein",
    "VotesNine": 63,
    "IdNine": 895,
    "": 16080
  },
  {
    "State Postal": "MN",
    "FIPS Code": 27023,
    "County Name": "Chippewa",
    "TOTAL VOTES CAST": 6176,
    "FirstOne": "Barack",
    "LastOne": "Obama",
    "VotesOne": 3083,
    "IdOne": 1918,
    "FirstTwo": "Mitt",
    "LastTwo": "Romney",
    "VotesTwo": 2967,
    "IdTwo": 893,
    "FirstThree": "Rocky",
    "LastThree": "Anderson",
    "VotesThree": 2,
    "IDThree": 43773,
    "FirstFour": "Jim",
    "LastFour": "Carlson",
    "VotesFour": 14,
    "IdFour": 62588,
    "FirstFive": "Virgil",
    "LastFive": "Goode",
    "VotesFive": 10,
    "IDFive": 713,
    "FirstSix": "James",
    "LastSix": "Harris",
    "VotesSix": 5,
    "IDSix": 3486,
    "FirstSeven": "Gary",
    "LastSeven": "Johnson",
    "VotesSeven": 72,
    "IDSeven": 31708,
    "FirstEight": "Peta",
    "LastEight": "Lindsay",
    "VotesEight": 1,
    "IDEight": 62562,
    "FirstNine": "Jill",
    "LastNine": "Stein",
    "VotesNine": 20,
    "IdNine": 895,
    "": 6176
  },
  {
    "State Postal": "MN",
    "FIPS Code": 27025,
    "County Name": "Chisago",
    "TOTAL VOTES CAST": 29331,
    "FirstOne": "Barack",
    "LastOne": "Obama",
    "VotesOne": 12524,
    "IdOne": 1918,
    "FirstTwo": "Mitt",
    "LastTwo": "Romney",
    "VotesTwo": 16227,
    "IdTwo": 893,
    "FirstThree": "Rocky",
    "LastThree": "Anderson",
    "VotesThree": 21,
    "IDThree": 43773,
    "FirstFour": "Jim",
    "LastFour": "Carlson",
    "VotesFour": 40,
    "IdFour": 62588,
    "FirstFive": "Virgil",
    "LastFive": "Goode",
    "VotesFive": 52,
    "IDFive": 713,
    "FirstSix": "James",
    "LastSix": "Harris",
    "VotesSix": 10,
    "IDSix": 3486,
    "FirstSeven": "Gary",
    "LastSeven": "Johnson",
    "VotesSeven": 338,
    "IDSeven": 31708,
    "FirstEight": "Peta",
    "LastEight": "Lindsay",
    "VotesEight": 5,
    "IDEight": 62562,
    "FirstNine": "Jill",
    "LastNine": "Stein",
    "VotesNine": 106,
    "IdNine": 895,
    "": 29331
  },
  {
    "State Postal": "MN",
    "FIPS Code": 27027,
    "County Name": "Clay",
    "TOTAL VOTES CAST": 28771,
    "FirstOne": "Barack",
    "LastOne": "Obama",
    "VotesOne": 15210,
    "IdOne": 1918,
    "FirstTwo": "Mitt",
    "LastTwo": "Romney",
    "VotesTwo": 12920,
    "IdTwo": 893,
    "FirstThree": "Rocky",
    "LastThree": "Anderson",
    "VotesThree": 30,
    "IDThree": 43773,
    "FirstFour": "Jim",
    "LastFour": "Carlson",
    "VotesFour": 28,
    "IdFour": 62588,
    "FirstFive": "Virgil",
    "LastFive": "Goode",
    "VotesFive": 38,
    "IDFive": 713,
    "FirstSix": "James",
    "LastSix": "Harris",
    "VotesSix": 15,
    "IDSix": 3486,
    "FirstSeven": "Gary",
    "LastSeven": "Johnson",
    "VotesSeven": 384,
    "IDSeven": 31708,
    "FirstEight": "Peta",
    "LastEight": "Lindsay",
    "VotesEight": 3,
    "IDEight": 62562,
    "FirstNine": "Jill",
    "LastNine": "Stein",
    "VotesNine": 134,
    "IdNine": 895,
    "": 28771
  },
  {
    "State Postal": "MN",
    "FIPS Code": 27029,
    "County Name": "Clearwater",
    "TOTAL VOTES CAST": 4183,
    "FirstOne": "Barack",
    "LastOne": "Obama",
    "VotesOne": 1753,
    "IdOne": 1918,
    "FirstTwo": "Mitt",
    "LastTwo": "Romney",
    "VotesTwo": 2359,
    "IdTwo": 893,
    "FirstThree": "Rocky",
    "LastThree": "Anderson",
    "VotesThree": 4,
    "IDThree": 43773,
    "FirstFour": "Jim",
    "LastFour": "Carlson",
    "VotesFour": 6,
    "IdFour": 62588,
    "FirstFive": "Virgil",
    "LastFive": "Goode",
    "VotesFive": 6,
    "IDFive": 713,
    "FirstSix": "James",
    "LastSix": "Harris",
    "VotesSix": 2,
    "IDSix": 3486,
    "FirstSeven": "Gary",
    "LastSeven": "Johnson",
    "VotesSeven": 36,
    "IDSeven": 31708,
    "FirstEight": "Peta",
    "LastEight": "Lindsay",
    "VotesEight": 1,
    "IDEight": 62562,
    "FirstNine": "Jill",
    "LastNine": "Stein",
    "VotesNine": 13,
    "IdNine": 895,
    "": 4183
  },
  {
    "State Postal": "MN",
    "FIPS Code": 27031,
    "County Name": "Cook",
    "TOTAL VOTES CAST": 3304,
    "FirstOne": "Barack",
    "LastOne": "Obama",
    "VotesOne": 1993,
    "IdOne": 1918,
    "FirstTwo": "Mitt",
    "LastTwo": "Romney",
    "VotesTwo": 1221,
    "IdTwo": 893,
    "FirstThree": "Rocky",
    "LastThree": "Anderson",
    "VotesThree": 2,
    "IDThree": 43773,
    "FirstFour": "Jim",
    "LastFour": "Carlson",
    "VotesFour": 2,
    "IdFour": 62588,
    "FirstFive": "Virgil",
    "LastFive": "Goode",
    "VotesFive": 10,
    "IDFive": 713,
    "FirstSix": "James",
    "LastSix": "Harris",
    "VotesSix": 0,
    "IDSix": 3486,
    "FirstSeven": "Gary",
    "LastSeven": "Johnson",
    "VotesSeven": 46,
    "IDSeven": 31708,
    "FirstEight": "Peta",
    "LastEight": "Lindsay",
    "VotesEight": 0,
    "IDEight": 62562,
    "FirstNine": "Jill",
    "LastNine": "Stein",
    "VotesNine": 26,
    "IdNine": 895,
    "": 3304
  },
  {
    "State Postal": "MN",
    "FIPS Code": 27033,
    "County Name": "Cottonwood",
    "TOTAL VOTES CAST": 5848,
    "FirstOne": "Barack",
    "LastOne": "Obama",
    "VotesOne": 2433,
    "IdOne": 1918,
    "FirstTwo": "Mitt",
    "LastTwo": "Romney",
    "VotesTwo": 3316,
    "IdTwo": 893,
    "FirstThree": "Rocky",
    "LastThree": "Anderson",
    "VotesThree": 2,
    "IDThree": 43773,
    "FirstFour": "Jim",
    "LastFour": "Carlson",
    "VotesFour": 7,
    "IdFour": 62588,
    "FirstFive": "Virgil",
    "LastFive": "Goode",
    "VotesFive": 15,
    "IDFive": 713,
    "FirstSix": "James",
    "LastSix": "Harris",
    "VotesSix": 4,
    "IDSix": 3486,
    "FirstSeven": "Gary",
    "LastSeven": "Johnson",
    "VotesSeven": 51,
    "IDSeven": 31708,
    "FirstEight": "Peta",
    "LastEight": "Lindsay",
    "VotesEight": 3,
    "IDEight": 62562,
    "FirstNine": "Jill",
    "LastNine": "Stein",
    "VotesNine": 15,
    "IdNine": 895,
    "": 5848
  },
  {
    "State Postal": "MN",
    "FIPS Code": 27035,
    "County Name": "Crow Wing",
    "TOTAL VOTES CAST": 34800,
    "FirstOne": "Barack",
    "LastOne": "Obama",
    "VotesOne": 14760,
    "IdOne": 1918,
    "FirstTwo": "Mitt",
    "LastTwo": "Romney",
    "VotesTwo": 19415,
    "IdTwo": 893,
    "FirstThree": "Rocky",
    "LastThree": "Anderson",
    "VotesThree": 22,
    "IDThree": 43773,
    "FirstFour": "Jim",
    "LastFour": "Carlson",
    "VotesFour": 45,
    "IdFour": 62588,
    "FirstFive": "Virgil",
    "LastFive": "Goode",
    "VotesFive": 62,
    "IDFive": 713,
    "FirstSix": "James",
    "LastSix": "Harris",
    "VotesSix": 8,
    "IDSix": 3486,
    "FirstSeven": "Gary",
    "LastSeven": "Johnson",
    "VotesSeven": 337,
    "IDSeven": 31708,
    "FirstEight": "Peta",
    "LastEight": "Lindsay",
    "VotesEight": 7,
    "IDEight": 62562,
    "FirstNine": "Jill",
    "LastNine": "Stein",
    "VotesNine": 133,
    "IdNine": 895,
    "": 34800
  },
  {
    "State Postal": "MN",
    "FIPS Code": 27037,
    "County Name": "Dakota",
    "TOTAL VOTES CAST": 230023,
    "FirstOne": "Barack",
    "LastOne": "Obama",
    "VotesOne": 116252,
    "IdOne": 1918,
    "FirstTwo": "Mitt",
    "LastTwo": "Romney",
    "VotesTwo": 109514,
    "IdTwo": 893,
    "FirstThree": "Rocky",
    "LastThree": "Anderson",
    "VotesThree": 125,
    "IDThree": 43773,
    "FirstFour": "Jim",
    "LastFour": "Carlson",
    "VotesFour": 186,
    "IdFour": 62588,
    "FirstFive": "Virgil",
    "LastFive": "Goode",
    "VotesFive": 260,
    "IDFive": 713,
    "FirstSix": "James",
    "LastSix": "Harris",
    "VotesSix": 52,
    "IDSix": 3486,
    "FirstSeven": "Gary",
    "LastSeven": "Johnson",
    "VotesSeven": 2746,
    "IDSeven": 31708,
    "FirstEight": "Peta",
    "LastEight": "Lindsay",
    "VotesEight": 17,
    "IDEight": 62562,
    "FirstNine": "Jill",
    "LastNine": "Stein",
    "VotesNine": 804,
    "IdNine": 895,
    "": 230023
  },
  {
    "State Postal": "MN",
    "FIPS Code": 27039,
    "County Name": "Dodge",
    "TOTAL VOTES CAST": 10272,
    "FirstOne": "Barack",
    "LastOne": "Obama",
    "VotesOne": 4487,
    "IdOne": 1918,
    "FirstTwo": "Mitt",
    "LastTwo": "Romney",
    "VotesTwo": 5522,
    "IdTwo": 893,
    "FirstThree": "Rocky",
    "LastThree": "Anderson",
    "VotesThree": 8,
    "IDThree": 43773,
    "FirstFour": "Jim",
    "LastFour": "Carlson",
    "VotesFour": 11,
    "IdFour": 62588,
    "FirstFive": "Virgil",
    "LastFive": "Goode",
    "VotesFive": 28,
    "IDFive": 713,
    "FirstSix": "James",
    "LastSix": "Harris",
    "VotesSix": 4,
    "IDSix": 3486,
    "FirstSeven": "Gary",
    "LastSeven": "Johnson",
    "VotesSeven": 158,
    "IDSeven": 31708,
    "FirstEight": "Peta",
    "LastEight": "Lindsay",
    "VotesEight": 1,
    "IDEight": 62562,
    "FirstNine": "Jill",
    "LastNine": "Stein",
    "VotesNine": 44,
    "IdNine": 895,
    "": 10272
  },
  {
    "State Postal": "MN",
    "FIPS Code": 27041,
    "County Name": "Douglas",
    "TOTAL VOTES CAST": 20917,
    "FirstOne": "Barack",
    "LastOne": "Obama",
    "VotesOne": 8665,
    "IdOne": 1918,
    "FirstTwo": "Mitt",
    "LastTwo": "Romney",
    "VotesTwo": 11905,
    "IdTwo": 893,
    "FirstThree": "Rocky",
    "LastThree": "Anderson",
    "VotesThree": 14,
    "IDThree": 43773,
    "FirstFour": "Jim",
    "LastFour": "Carlson",
    "VotesFour": 28,
    "IdFour": 62588,
    "FirstFive": "Virgil",
    "LastFive": "Goode",
    "VotesFive": 35,
    "IDFive": 713,
    "FirstSix": "James",
    "LastSix": "Harris",
    "VotesSix": 5,
    "IDSix": 3486,
    "FirstSeven": "Gary",
    "LastSeven": "Johnson",
    "VotesSeven": 184,
    "IDSeven": 31708,
    "FirstEight": "Peta",
    "LastEight": "Lindsay",
    "VotesEight": 4,
    "IDEight": 62562,
    "FirstNine": "Jill",
    "LastNine": "Stein",
    "VotesNine": 66,
    "IdNine": 895,
    "": 20917
  },
  {
    "State Postal": "MN",
    "FIPS Code": 27043,
    "County Name": "Faribault",
    "TOTAL VOTES CAST": 7689,
    "FirstOne": "Barack",
    "LastOne": "Obama",
    "VotesOne": 3407,
    "IdOne": 1918,
    "FirstTwo": "Mitt",
    "LastTwo": "Romney",
    "VotesTwo": 4104,
    "IdTwo": 893,
    "FirstThree": "Rocky",
    "LastThree": "Anderson",
    "VotesThree": 5,
    "IDThree": 43773,
    "FirstFour": "Jim",
    "LastFour": "Carlson",
    "VotesFour": 13,
    "IdFour": 62588,
    "FirstFive": "Virgil",
    "LastFive": "Goode",
    "VotesFive": 14,
    "IDFive": 713,
    "FirstSix": "James",
    "LastSix": "Harris",
    "VotesSix": 5,
    "IDSix": 3486,
    "FirstSeven": "Gary",
    "LastSeven": "Johnson",
    "VotesSeven": 98,
    "IDSeven": 31708,
    "FirstEight": "Peta",
    "LastEight": "Lindsay",
    "VotesEight": 0,
    "IDEight": 62562,
    "FirstNine": "Jill",
    "LastNine": "Stein",
    "VotesNine": 36,
    "IdNine": 895,
    "": 7689
  },
  {
    "State Postal": "MN",
    "FIPS Code": 27045,
    "County Name": "Fillmore",
    "TOTAL VOTES CAST": 10854,
    "FirstOne": "Barack",
    "LastOne": "Obama",
    "VotesOne": 5713,
    "IdOne": 1918,
    "FirstTwo": "Mitt",
    "LastTwo": "Romney",
    "VotesTwo": 4913,
    "IdTwo": 893,
    "FirstThree": "Rocky",
    "LastThree": "Anderson",
    "VotesThree": 10,
    "IDThree": 43773,
    "FirstFour": "Jim",
    "LastFour": "Carlson",
    "VotesFour": 18,
    "IdFour": 62588,
    "FirstFive": "Virgil",
    "LastFive": "Goode",
    "VotesFive": 17,
    "IDFive": 713,
    "FirstSix": "James",
    "LastSix": "Harris",
    "VotesSix": 2,
    "IDSix": 3486,
    "FirstSeven": "Gary",
    "LastSeven": "Johnson",
    "VotesSeven": 143,
    "IDSeven": 31708,
    "FirstEight": "Peta",
    "LastEight": "Lindsay",
    "VotesEight": 4,
    "IDEight": 62562,
    "FirstNine": "Jill",
    "LastNine": "Stein",
    "VotesNine": 33,
    "IdNine": 895,
    "": 10854
  },
  {
    "State Postal": "MN",
    "FIPS Code": 27047,
    "County Name": "Freeborn",
    "TOTAL VOTES CAST": 16645,
    "FirstOne": "Barack",
    "LastOne": "Obama",
    "VotesOne": 9327,
    "IdOne": 1918,
    "FirstTwo": "Mitt",
    "LastTwo": "Romney",
    "VotesTwo": 6970,
    "IdTwo": 893,
    "FirstThree": "Rocky",
    "LastThree": "Anderson",
    "VotesThree": 8,
    "IDThree": 43773,
    "FirstFour": "Jim",
    "LastFour": "Carlson",
    "VotesFour": 33,
    "IdFour": 62588,
    "FirstFive": "Virgil",
    "LastFive": "Goode",
    "VotesFive": 24,
    "IDFive": 713,
    "FirstSix": "James",
    "LastSix": "Harris",
    "VotesSix": 8,
    "IDSix": 3486,
    "FirstSeven": "Gary",
    "LastSeven": "Johnson",
    "VotesSeven": 197,
    "IDSeven": 31708,
    "FirstEight": "Peta",
    "LastEight": "Lindsay",
    "VotesEight": 3,
    "IDEight": 62562,
    "FirstNine": "Jill",
    "LastNine": "Stein",
    "VotesNine": 64,
    "IdNine": 895,
    "": 16645
  },
  {
    "State Postal": "MN",
    "FIPS Code": 27049,
    "County Name": "Goodhue",
    "TOTAL VOTES CAST": 25701,
    "FirstOne": "Barack",
    "LastOne": "Obama",
    "VotesOne": 12212,
    "IdOne": 1918,
    "FirstTwo": "Mitt",
    "LastTwo": "Romney",
    "VotesTwo": 12986,
    "IdTwo": 893,
    "FirstThree": "Rocky",
    "LastThree": "Anderson",
    "VotesThree": 12,
    "IDThree": 43773,
    "FirstFour": "Jim",
    "LastFour": "Carlson",
    "VotesFour": 29,
    "IdFour": 62588,
    "FirstFive": "Virgil",
    "LastFive": "Goode",
    "VotesFive": 34,
    "IDFive": 713,
    "FirstSix": "James",
    "LastSix": "Harris",
    "VotesSix": 9,
    "IDSix": 3486,
    "FirstSeven": "Gary",
    "LastSeven": "Johnson",
    "VotesSeven": 301,
    "IDSeven": 31708,
    "FirstEight": "Peta",
    "LastEight": "Lindsay",
    "VotesEight": 4,
    "IDEight": 62562,
    "FirstNine": "Jill",
    "LastNine": "Stein",
    "VotesNine": 107,
    "IdNine": 895,
    "": 25701
  },
  {
    "State Postal": "MN",
    "FIPS Code": 27051,
    "County Name": "Grant",
    "TOTAL VOTES CAST": 3471,
    "FirstOne": "Barack",
    "LastOne": "Obama",
    "VotesOne": 1647,
    "IdOne": 1918,
    "FirstTwo": "Mitt",
    "LastTwo": "Romney",
    "VotesTwo": 1748,
    "IdTwo": 893,
    "FirstThree": "Rocky",
    "LastThree": "Anderson",
    "VotesThree": 2,
    "IDThree": 43773,
    "FirstFour": "Jim",
    "LastFour": "Carlson",
    "VotesFour": 11,
    "IdFour": 62588,
    "FirstFive": "Virgil",
    "LastFive": "Goode",
    "VotesFive": 6,
    "IDFive": 713,
    "FirstSix": "James",
    "LastSix": "Harris",
    "VotesSix": 1,
    "IDSix": 3486,
    "FirstSeven": "Gary",
    "LastSeven": "Johnson",
    "VotesSeven": 40,
    "IDSeven": 31708,
    "FirstEight": "Peta",
    "LastEight": "Lindsay",
    "VotesEight": 0,
    "IDEight": 62562,
    "FirstNine": "Jill",
    "LastNine": "Stein",
    "VotesNine": 12,
    "IdNine": 895,
    "": 3471
  },
  {
    "State Postal": "MN",
    "FIPS Code": 27053,
    "County Name": "Hennepin",
    "TOTAL VOTES CAST": 677965,
    "FirstOne": "Barack",
    "LastOne": "Obama",
    "VotesOne": 423979,
    "IdOne": 1918,
    "FirstTwo": "Mitt",
    "LastTwo": "Romney",
    "VotesTwo": 240073,
    "IdTwo": 893,
    "FirstThree": "Rocky",
    "LastThree": "Anderson",
    "VotesThree": 470,
    "IDThree": 43773,
    "FirstFour": "Jim",
    "LastFour": "Carlson",
    "VotesFour": 388,
    "IdFour": 62588,
    "FirstFive": "Virgil",
    "LastFive": "Goode",
    "VotesFive": 526,
    "IDFive": 713,
    "FirstSix": "James",
    "LastSix": "Harris",
    "VotesSix": 212,
    "IDSix": 3486,
    "FirstSeven": "Gary",
    "LastSeven": "Johnson",
    "VotesSeven": 8289,
    "IDSeven": 31708,
    "FirstEight": "Peta",
    "LastEight": "Lindsay",
    "VotesEight": 118,
    "IDEight": 62562,
    "FirstNine": "Jill",
    "LastNine": "Stein",
    "VotesNine": 3743,
    "IdNine": 895,
    "": 677965
  },
  {
    "State Postal": "MN",
    "FIPS Code": 27055,
    "County Name": "Houston",
    "TOTAL VOTES CAST": 10422,
    "FirstOne": "Barack",
    "LastOne": "Obama",
    "VotesOne": 5281,
    "IdOne": 1918,
    "FirstTwo": "Mitt",
    "LastTwo": "Romney",
    "VotesTwo": 4951,
    "IdTwo": 893,
    "FirstThree": "Rocky",
    "LastThree": "Anderson",
    "VotesThree": 6,
    "IDThree": 43773,
    "FirstFour": "Jim",
    "LastFour": "Carlson",
    "VotesFour": 16,
    "IdFour": 62588,
    "FirstFive": "Virgil",
    "LastFive": "Goode",
    "VotesFive": 12,
    "IDFive": 713,
    "FirstSix": "James",
    "LastSix": "Harris",
    "VotesSix": 0,
    "IDSix": 3486,
    "FirstSeven": "Gary",
    "LastSeven": "Johnson",
    "VotesSeven": 105,
    "IDSeven": 31708,
    "FirstEight": "Peta",
    "LastEight": "Lindsay",
    "VotesEight": 1,
    "IDEight": 62562,
    "FirstNine": "Jill",
    "LastNine": "Stein",
    "VotesNine": 45,
    "IdNine": 895,
    "": 10422
  },
  {
    "State Postal": "MN",
    "FIPS Code": 27057,
    "County Name": "Hubbard",
    "TOTAL VOTES CAST": 11482,
    "FirstOne": "Barack",
    "LastOne": "Obama",
    "VotesOne": 4676,
    "IdOne": 1918,
    "FirstTwo": "Mitt",
    "LastTwo": "Romney",
    "VotesTwo": 6622,
    "IdTwo": 893,
    "FirstThree": "Rocky",
    "LastThree": "Anderson",
    "VotesThree": 9,
    "IDThree": 43773,
    "FirstFour": "Jim",
    "LastFour": "Carlson",
    "VotesFour": 14,
    "IdFour": 62588,
    "FirstFive": "Virgil",
    "LastFive": "Goode",
    "VotesFive": 23,
    "IDFive": 713,
    "FirstSix": "James",
    "LastSix": "Harris",
    "VotesSix": 4,
    "IDSix": 3486,
    "FirstSeven": "Gary",
    "LastSeven": "Johnson",
    "VotesSeven": 84,
    "IDSeven": 31708,
    "FirstEight": "Peta",
    "LastEight": "Lindsay",
    "VotesEight": 0,
    "IDEight": 62562,
    "FirstNine": "Jill",
    "LastNine": "Stein",
    "VotesNine": 46,
    "IdNine": 895,
    "": 11482
  },
  {
    "State Postal": "MN",
    "FIPS Code": 27059,
    "County Name": "Isanti",
    "TOTAL VOTES CAST": 20131,
    "FirstOne": "Barack",
    "LastOne": "Obama",
    "VotesOne": 8024,
    "IdOne": 1918,
    "FirstTwo": "Mitt",
    "LastTwo": "Romney",
    "VotesTwo": 11675,
    "IdTwo": 893,
    "FirstThree": "Rocky",
    "LastThree": "Anderson",
    "VotesThree": 21,
    "IDThree": 43773,
    "FirstFour": "Jim",
    "LastFour": "Carlson",
    "VotesFour": 39,
    "IdFour": 62588,
    "FirstFive": "Virgil",
    "LastFive": "Goode",
    "VotesFive": 43,
    "IDFive": 713,
    "FirstSix": "James",
    "LastSix": "Harris",
    "VotesSix": 18,
    "IDSix": 3486,
    "FirstSeven": "Gary",
    "LastSeven": "Johnson",
    "VotesSeven": 227,
    "IDSeven": 31708,
    "FirstEight": "Peta",
    "LastEight": "Lindsay",
    "VotesEight": 1,
    "IDEight": 62562,
    "FirstNine": "Jill",
    "LastNine": "Stein",
    "VotesNine": 68,
    "IdNine": 895,
    "": 20131
  },
  {
    "State Postal": "MN",
    "FIPS Code": 27061,
    "County Name": "Itasca",
    "TOTAL VOTES CAST": 23833,
    "FirstOne": "Barack",
    "LastOne": "Obama",
    "VotesOne": 12852,
    "IdOne": 1918,
    "FirstTwo": "Mitt",
    "LastTwo": "Romney",
    "VotesTwo": 10500,
    "IdTwo": 893,
    "FirstThree": "Rocky",
    "LastThree": "Anderson",
    "VotesThree": 19,
    "IDThree": 43773,
    "FirstFour": "Jim",
    "LastFour": "Carlson",
    "VotesFour": 61,
    "IdFour": 62588,
    "FirstFive": "Virgil",
    "LastFive": "Goode",
    "VotesFive": 58,
    "IDFive": 713,
    "FirstSix": "James",
    "LastSix": "Harris",
    "VotesSix": 13,
    "IDSix": 3486,
    "FirstSeven": "Gary",
    "LastSeven": "Johnson",
    "VotesSeven": 227,
    "IDSeven": 31708,
    "FirstEight": "Peta",
    "LastEight": "Lindsay",
    "VotesEight": 3,
    "IDEight": 62562,
    "FirstNine": "Jill",
    "LastNine": "Stein",
    "VotesNine": 90,
    "IdNine": 895,
    "": 23833
  },
  {
    "State Postal": "MN",
    "FIPS Code": 27063,
    "County Name": "Jackson",
    "TOTAL VOTES CAST": 5415,
    "FirstOne": "Barack",
    "LastOne": "Obama",
    "VotesOne": 2268,
    "IdOne": 1918,
    "FirstTwo": "Mitt",
    "LastTwo": "Romney",
    "VotesTwo": 3044,
    "IdTwo": 893,
    "FirstThree": "Rocky",
    "LastThree": "Anderson",
    "VotesThree": 0,
    "IDThree": 43773,
    "FirstFour": "Jim",
    "LastFour": "Carlson",
    "VotesFour": 7,
    "IdFour": 62588,
    "FirstFive": "Virgil",
    "LastFive": "Goode",
    "VotesFive": 10,
    "IDFive": 713,
    "FirstSix": "James",
    "LastSix": "Harris",
    "VotesSix": 1,
    "IDSix": 3486,
    "FirstSeven": "Gary",
    "LastSeven": "Johnson",
    "VotesSeven": 62,
    "IDSeven": 31708,
    "FirstEight": "Peta",
    "LastEight": "Lindsay",
    "VotesEight": 1,
    "IDEight": 62562,
    "FirstNine": "Jill",
    "LastNine": "Stein",
    "VotesNine": 21,
    "IdNine": 895,
    "": 5415
  },
  {
    "State Postal": "MN",
    "FIPS Code": 27065,
    "County Name": "Kanabec",
    "TOTAL VOTES CAST": 8107,
    "FirstOne": "Barack",
    "LastOne": "Obama",
    "VotesOne": 3586,
    "IdOne": 1918,
    "FirstTwo": "Mitt",
    "LastTwo": "Romney",
    "VotesTwo": 4319,
    "IdTwo": 893,
    "FirstThree": "Rocky",
    "LastThree": "Anderson",
    "VotesThree": 4,
    "IDThree": 43773,
    "FirstFour": "Jim",
    "LastFour": "Carlson",
    "VotesFour": 22,
    "IdFour": 62588,
    "FirstFive": "Virgil",
    "LastFive": "Goode",
    "VotesFive": 26,
    "IDFive": 713,
    "FirstSix": "James",
    "LastSix": "Harris",
    "VotesSix": 6,
    "IDSix": 3486,
    "FirstSeven": "Gary",
    "LastSeven": "Johnson",
    "VotesSeven": 103,
    "IDSeven": 31708,
    "FirstEight": "Peta",
    "LastEight": "Lindsay",
    "VotesEight": 0,
    "IDEight": 62562,
    "FirstNine": "Jill",
    "LastNine": "Stein",
    "VotesNine": 39,
    "IdNine": 895,
    "": 8107
  },
  {
    "State Postal": "MN",
    "FIPS Code": 27067,
    "County Name": "Kandiyohi",
    "TOTAL VOTES CAST": 21403,
    "FirstOne": "Barack",
    "LastOne": "Obama",
    "VotesOne": 9806,
    "IdOne": 1918,
    "FirstTwo": "Mitt",
    "LastTwo": "Romney",
    "VotesTwo": 11239,
    "IdTwo": 893,
    "FirstThree": "Rocky",
    "LastThree": "Anderson",
    "VotesThree": 14,
    "IDThree": 43773,
    "FirstFour": "Jim",
    "LastFour": "Carlson",
    "VotesFour": 25,
    "IdFour": 62588,
    "FirstFive": "Virgil",
    "LastFive": "Goode",
    "VotesFive": 25,
    "IDFive": 713,
    "FirstSix": "James",
    "LastSix": "Harris",
    "VotesSix": 6,
    "IDSix": 3486,
    "FirstSeven": "Gary",
    "LastSeven": "Johnson",
    "VotesSeven": 214,
    "IDSeven": 31708,
    "FirstEight": "Peta",
    "LastEight": "Lindsay",
    "VotesEight": 3,
    "IDEight": 62562,
    "FirstNine": "Jill",
    "LastNine": "Stein",
    "VotesNine": 59,
    "IdNine": 895,
    "": 21403
  },
  {
    "State Postal": "MN",
    "FIPS Code": 27069,
    "County Name": "Kittson",
    "TOTAL VOTES CAST": 2405,
    "FirstOne": "Barack",
    "LastOne": "Obama",
    "VotesOne": 1241,
    "IdOne": 1918,
    "FirstTwo": "Mitt",
    "LastTwo": "Romney",
    "VotesTwo": 1095,
    "IdTwo": 893,
    "FirstThree": "Rocky",
    "LastThree": "Anderson",
    "VotesThree": 0,
    "IDThree": 43773,
    "FirstFour": "Jim",
    "LastFour": "Carlson",
    "VotesFour": 11,
    "IdFour": 62588,
    "FirstFive": "Virgil",
    "LastFive": "Goode",
    "VotesFive": 7,
    "IDFive": 713,
    "FirstSix": "James",
    "LastSix": "Harris",
    "VotesSix": 1,
    "IDSix": 3486,
    "FirstSeven": "Gary",
    "LastSeven": "Johnson",
    "VotesSeven": 36,
    "IDSeven": 31708,
    "FirstEight": "Peta",
    "LastEight": "Lindsay",
    "VotesEight": 0,
    "IDEight": 62562,
    "FirstNine": "Jill",
    "LastNine": "Stein",
    "VotesNine": 14,
    "IdNine": 895,
    "": 2405
  },
  {
    "State Postal": "MN",
    "FIPS Code": 27071,
    "County Name": "Koochiching",
    "TOTAL VOTES CAST": 6432,
    "FirstOne": "Barack",
    "LastOne": "Obama",
    "VotesOne": 3451,
    "IdOne": 1918,
    "FirstTwo": "Mitt",
    "LastTwo": "Romney",
    "VotesTwo": 2841,
    "IdTwo": 893,
    "FirstThree": "Rocky",
    "LastThree": "Anderson",
    "VotesThree": 6,
    "IDThree": 43773,
    "FirstFour": "Jim",
    "LastFour": "Carlson",
    "VotesFour": 17,
    "IdFour": 62588,
    "FirstFive": "Virgil",
    "LastFive": "Goode",
    "VotesFive": 12,
    "IDFive": 713,
    "FirstSix": "James",
    "LastSix": "Harris",
    "VotesSix": 4,
    "IDSix": 3486,
    "FirstSeven": "Gary",
    "LastSeven": "Johnson",
    "VotesSeven": 76,
    "IDSeven": 31708,
    "FirstEight": "Peta",
    "LastEight": "Lindsay",
    "VotesEight": 0,
    "IDEight": 62562,
    "FirstNine": "Jill",
    "LastNine": "Stein",
    "VotesNine": 20,
    "IdNine": 895,
    "": 6432
  },
  {
    "State Postal": "MN",
    "FIPS Code": 27073,
    "County Name": "Lac Qui Parle",
    "TOTAL VOTES CAST": 3974,
    "FirstOne": "Barack",
    "LastOne": "Obama",
    "VotesOne": 1974,
    "IdOne": 1918,
    "FirstTwo": "Mitt",
    "LastTwo": "Romney",
    "VotesTwo": 1938,
    "IdTwo": 893,
    "FirstThree": "Rocky",
    "LastThree": "Anderson",
    "VotesThree": 3,
    "IDThree": 43773,
    "FirstFour": "Jim",
    "LastFour": "Carlson",
    "VotesFour": 1,
    "IdFour": 62588,
    "FirstFive": "Virgil",
    "LastFive": "Goode",
    "VotesFive": 5,
    "IDFive": 713,
    "FirstSix": "James",
    "LastSix": "Harris",
    "VotesSix": 3,
    "IDSix": 3486,
    "FirstSeven": "Gary",
    "LastSeven": "Johnson",
    "VotesSeven": 33,
    "IDSeven": 31708,
    "FirstEight": "Peta",
    "LastEight": "Lindsay",
    "VotesEight": 0,
    "IDEight": 62562,
    "FirstNine": "Jill",
    "LastNine": "Stein",
    "VotesNine": 15,
    "IdNine": 895,
    "": 3974
  },
  {
    "State Postal": "MN",
    "FIPS Code": 27075,
    "County Name": "Lake",
    "TOTAL VOTES CAST": 6797,
    "FirstOne": "Barack",
    "LastOne": "Obama",
    "VotesOne": 4043,
    "IdOne": 1918,
    "FirstTwo": "Mitt",
    "LastTwo": "Romney",
    "VotesTwo": 2610,
    "IdTwo": 893,
    "FirstThree": "Rocky",
    "LastThree": "Anderson",
    "VotesThree": 3,
    "IDThree": 43773,
    "FirstFour": "Jim",
    "LastFour": "Carlson",
    "VotesFour": 15,
    "IdFour": 62588,
    "FirstFive": "Virgil",
    "LastFive": "Goode",
    "VotesFive": 16,
    "IDFive": 713,
    "FirstSix": "James",
    "LastSix": "Harris",
    "VotesSix": 0,
    "IDSix": 3486,
    "FirstSeven": "Gary",
    "LastSeven": "Johnson",
    "VotesSeven": 63,
    "IDSeven": 31708,
    "FirstEight": "Peta",
    "LastEight": "Lindsay",
    "VotesEight": 0,
    "IDEight": 62562,
    "FirstNine": "Jill",
    "LastNine": "Stein",
    "VotesNine": 44,
    "IdNine": 895,
    "": 6797
  },
  {
    "State Postal": "MN",
    "FIPS Code": 27077,
    "County Name": "Lake of the Woods",
    "TOTAL VOTES CAST": 2220,
    "FirstOne": "Barack",
    "LastOne": "Obama",
    "VotesOne": 859,
    "IdOne": 1918,
    "FirstTwo": "Mitt",
    "LastTwo": "Romney",
    "VotesTwo": 1306,
    "IdTwo": 893,
    "FirstThree": "Rocky",
    "LastThree": "Anderson",
    "VotesThree": 1,
    "IDThree": 43773,
    "FirstFour": "Jim",
    "LastFour": "Carlson",
    "VotesFour": 8,
    "IdFour": 62588,
    "FirstFive": "Virgil",
    "LastFive": "Goode",
    "VotesFive": 8,
    "IDFive": 713,
    "FirstSix": "James",
    "LastSix": "Harris",
    "VotesSix": 3,
    "IDSix": 3486,
    "FirstSeven": "Gary",
    "LastSeven": "Johnson",
    "VotesSeven": 23,
    "IDSeven": 31708,
    "FirstEight": "Peta",
    "LastEight": "Lindsay",
    "VotesEight": 0,
    "IDEight": 62562,
    "FirstNine": "Jill",
    "LastNine": "Stein",
    "VotesNine": 9,
    "IdNine": 895,
    "": 2220
  },
  {
    "State Postal": "MN",
    "FIPS Code": 27079,
    "County Name": "Le Sueur",
    "TOTAL VOTES CAST": 14730,
    "FirstOne": "Barack",
    "LastOne": "Obama",
    "VotesOne": 6753,
    "IdOne": 1918,
    "FirstTwo": "Mitt",
    "LastTwo": "Romney",
    "VotesTwo": 7714,
    "IdTwo": 893,
    "FirstThree": "Rocky",
    "LastThree": "Anderson",
    "VotesThree": 9,
    "IDThree": 43773,
    "FirstFour": "Jim",
    "LastFour": "Carlson",
    "VotesFour": 27,
    "IdFour": 62588,
    "FirstFive": "Virgil",
    "LastFive": "Goode",
    "VotesFive": 23,
    "IDFive": 713,
    "FirstSix": "James",
    "LastSix": "Harris",
    "VotesSix": 7,
    "IDSix": 3486,
    "FirstSeven": "Gary",
    "LastSeven": "Johnson",
    "VotesSeven": 139,
    "IDSeven": 31708,
    "FirstEight": "Peta",
    "LastEight": "Lindsay",
    "VotesEight": 1,
    "IDEight": 62562,
    "FirstNine": "Jill",
    "LastNine": "Stein",
    "VotesNine": 50,
    "IdNine": 895,
    "": 14730
  },
  {
    "State Postal": "MN",
    "FIPS Code": 27081,
    "County Name": "Lincoln",
    "TOTAL VOTES CAST": 3113,
    "FirstOne": "Barack",
    "LastOne": "Obama",
    "VotesOne": 1428,
    "IdOne": 1918,
    "FirstTwo": "Mitt",
    "LastTwo": "Romney",
    "VotesTwo": 1594,
    "IdTwo": 893,
    "FirstThree": "Rocky",
    "LastThree": "Anderson",
    "VotesThree": 6,
    "IDThree": 43773,
    "FirstFour": "Jim",
    "LastFour": "Carlson",
    "VotesFour": 7,
    "IdFour": 62588,
    "FirstFive": "Virgil",
    "LastFive": "Goode",
    "VotesFive": 13,
    "IDFive": 713,
    "FirstSix": "James",
    "LastSix": "Harris",
    "VotesSix": 3,
    "IDSix": 3486,
    "FirstSeven": "Gary",
    "LastSeven": "Johnson",
    "VotesSeven": 41,
    "IDSeven": 31708,
    "FirstEight": "Peta",
    "LastEight": "Lindsay",
    "VotesEight": 0,
    "IDEight": 62562,
    "FirstNine": "Jill",
    "LastNine": "Stein",
    "VotesNine": 18,
    "IdNine": 895,
    "": 3113
  },
  {
    "State Postal": "MN",
    "FIPS Code": 27083,
    "County Name": "Lyon",
    "TOTAL VOTES CAST": 12334,
    "FirstOne": "Barack",
    "LastOne": "Obama",
    "VotesOne": 5465,
    "IdOne": 1918,
    "FirstTwo": "Mitt",
    "LastTwo": "Romney",
    "VotesTwo": 6595,
    "IdTwo": 893,
    "FirstThree": "Rocky",
    "LastThree": "Anderson",
    "VotesThree": 9,
    "IDThree": 43773,
    "FirstFour": "Jim",
    "LastFour": "Carlson",
    "VotesFour": 27,
    "IdFour": 62588,
    "FirstFive": "Virgil",
    "LastFive": "Goode",
    "VotesFive": 17,
    "IDFive": 713,
    "FirstSix": "James",
    "LastSix": "Harris",
    "VotesSix": 5,
    "IDSix": 3486,
    "FirstSeven": "Gary",
    "LastSeven": "Johnson",
    "VotesSeven": 156,
    "IDSeven": 31708,
    "FirstEight": "Peta",
    "LastEight": "Lindsay",
    "VotesEight": 0,
    "IDEight": 62562,
    "FirstNine": "Jill",
    "LastNine": "Stein",
    "VotesNine": 48,
    "IdNine": 895,
    "": 12334
  },
  {
    "State Postal": "MN",
    "FIPS Code": 27085,
    "County Name": "McLeod",
    "TOTAL VOTES CAST": 18455,
    "FirstOne": "Barack",
    "LastOne": "Obama",
    "VotesOne": 6970,
    "IdOne": 1918,
    "FirstTwo": "Mitt",
    "LastTwo": "Romney",
    "VotesTwo": 11069,
    "IdTwo": 893,
    "FirstThree": "Rocky",
    "LastThree": "Anderson",
    "VotesThree": 10,
    "IDThree": 43773,
    "FirstFour": "Jim",
    "LastFour": "Carlson",
    "VotesFour": 29,
    "IdFour": 62588,
    "FirstFive": "Virgil",
    "LastFive": "Goode",
    "VotesFive": 50,
    "IDFive": 713,
    "FirstSix": "James",
    "LastSix": "Harris",
    "VotesSix": 10,
    "IDSix": 3486,
    "FirstSeven": "Gary",
    "LastSeven": "Johnson",
    "VotesSeven": 235,
    "IDSeven": 31708,
    "FirstEight": "Peta",
    "LastEight": "Lindsay",
    "VotesEight": 5,
    "IDEight": 62562,
    "FirstNine": "Jill",
    "LastNine": "Stein",
    "VotesNine": 68,
    "IdNine": 895,
    "": 18455
  },
  {
    "State Postal": "MN",
    "FIPS Code": 27087,
    "County Name": "Mahnomen",
    "TOTAL VOTES CAST": 2179,
    "FirstOne": "Barack",
    "LastOne": "Obama",
    "VotesOne": 1276,
    "IdOne": 1918,
    "FirstTwo": "Mitt",
    "LastTwo": "Romney",
    "VotesTwo": 871,
    "IdTwo": 893,
    "FirstThree": "Rocky",
    "LastThree": "Anderson",
    "VotesThree": 1,
    "IDThree": 43773,
    "FirstFour": "Jim",
    "LastFour": "Carlson",
    "VotesFour": 4,
    "IdFour": 62588,
    "FirstFive": "Virgil",
    "LastFive": "Goode",
    "VotesFive": 1,
    "IDFive": 713,
    "FirstSix": "James",
    "LastSix": "Harris",
    "VotesSix": 2,
    "IDSix": 3486,
    "FirstSeven": "Gary",
    "LastSeven": "Johnson",
    "VotesSeven": 14,
    "IDSeven": 31708,
    "FirstEight": "Peta",
    "LastEight": "Lindsay",
    "VotesEight": 0,
    "IDEight": 62562,
    "FirstNine": "Jill",
    "LastNine": "Stein",
    "VotesNine": 10,
    "IdNine": 895,
    "": 2179
  },
  {
    "State Postal": "MN",
    "FIPS Code": 27089,
    "County Name": "Marshall",
    "TOTAL VOTES CAST": 4335,
    "FirstOne": "Barack",
    "LastOne": "Obama",
    "VotesOne": 1854,
    "IdOne": 1918,
    "FirstTwo": "Mitt",
    "LastTwo": "Romney",
    "VotesTwo": 2380,
    "IdTwo": 893,
    "FirstThree": "Rocky",
    "LastThree": "Anderson",
    "VotesThree": 5,
    "IDThree": 43773,
    "FirstFour": "Jim",
    "LastFour": "Carlson",
    "VotesFour": 16,
    "IdFour": 62588,
    "FirstFive": "Virgil",
    "LastFive": "Goode",
    "VotesFive": 8,
    "IDFive": 713,
    "FirstSix": "James",
    "LastSix": "Harris",
    "VotesSix": 5,
    "IDSix": 3486,
    "FirstSeven": "Gary",
    "LastSeven": "Johnson",
    "VotesSeven": 42,
    "IDSeven": 31708,
    "FirstEight": "Peta",
    "LastEight": "Lindsay",
    "VotesEight": 1,
    "IDEight": 62562,
    "FirstNine": "Jill",
    "LastNine": "Stein",
    "VotesNine": 19,
    "IdNine": 895,
    "": 4335
  },
  {
    "State Postal": "MN",
    "FIPS Code": 27091,
    "County Name": "Martin",
    "TOTAL VOTES CAST": 10927,
    "FirstOne": "Barack",
    "LastOne": "Obama",
    "VotesOne": 4054,
    "IdOne": 1918,
    "FirstTwo": "Mitt",
    "LastTwo": "Romney",
    "VotesTwo": 6657,
    "IdTwo": 893,
    "FirstThree": "Rocky",
    "LastThree": "Anderson",
    "VotesThree": 11,
    "IDThree": 43773,
    "FirstFour": "Jim",
    "LastFour": "Carlson",
    "VotesFour": 24,
    "IdFour": 62588,
    "FirstFive": "Virgil",
    "LastFive": "Goode",
    "VotesFive": 8,
    "IDFive": 713,
    "FirstSix": "James",
    "LastSix": "Harris",
    "VotesSix": 8,
    "IDSix": 3486,
    "FirstSeven": "Gary",
    "LastSeven": "Johnson",
    "VotesSeven": 130,
    "IDSeven": 31708,
    "FirstEight": "Peta",
    "LastEight": "Lindsay",
    "VotesEight": 0,
    "IDEight": 62562,
    "FirstNine": "Jill",
    "LastNine": "Stein",
    "VotesNine": 29,
    "IdNine": 895,
    "": 10927
  },
  {
    "State Postal": "MN",
    "FIPS Code": 27093,
    "County Name": "Meeker",
    "TOTAL VOTES CAST": 12167,
    "FirstOne": "Barack",
    "LastOne": "Obama",
    "VotesOne": 4969,
    "IdOne": 1918,
    "FirstTwo": "Mitt",
    "LastTwo": "Romney",
    "VotesTwo": 6913,
    "IdTwo": 893,
    "FirstThree": "Rocky",
    "LastThree": "Anderson",
    "VotesThree": 10,
    "IDThree": 43773,
    "FirstFour": "Jim",
    "LastFour": "Carlson",
    "VotesFour": 21,
    "IdFour": 62588,
    "FirstFive": "Virgil",
    "LastFive": "Goode",
    "VotesFive": 34,
    "IDFive": 713,
    "FirstSix": "James",
    "LastSix": "Harris",
    "VotesSix": 4,
    "IDSix": 3486,
    "FirstSeven": "Gary",
    "LastSeven": "Johnson",
    "VotesSeven": 156,
    "IDSeven": 31708,
    "FirstEight": "Peta",
    "LastEight": "Lindsay",
    "VotesEight": 2,
    "IDEight": 62562,
    "FirstNine": "Jill",
    "LastNine": "Stein",
    "VotesNine": 54,
    "IdNine": 895,
    "": 12167
  },
  {
    "State Postal": "MN",
    "FIPS Code": 27095,
    "County Name": "Mille Lacs",
    "TOTAL VOTES CAST": 13047,
    "FirstOne": "Barack",
    "LastOne": "Obama",
    "VotesOne": 5829,
    "IdOne": 1918,
    "FirstTwo": "Mitt",
    "LastTwo": "Romney",
    "VotesTwo": 6951,
    "IdTwo": 893,
    "FirstThree": "Rocky",
    "LastThree": "Anderson",
    "VotesThree": 13,
    "IDThree": 43773,
    "FirstFour": "Jim",
    "LastFour": "Carlson",
    "VotesFour": 26,
    "IdFour": 62588,
    "FirstFive": "Virgil",
    "LastFive": "Goode",
    "VotesFive": 27,
    "IDFive": 713,
    "FirstSix": "James",
    "LastSix": "Harris",
    "VotesSix": 6,
    "IDSix": 3486,
    "FirstSeven": "Gary",
    "LastSeven": "Johnson",
    "VotesSeven": 136,
    "IDSeven": 31708,
    "FirstEight": "Peta",
    "LastEight": "Lindsay",
    "VotesEight": 3,
    "IDEight": 62562,
    "FirstNine": "Jill",
    "LastNine": "Stein",
    "VotesNine": 51,
    "IdNine": 895,
    "": 13047
  },
  {
    "State Postal": "MN",
    "FIPS Code": 27097,
    "County Name": "Morrison",
    "TOTAL VOTES CAST": 16662,
    "FirstOne": "Barack",
    "LastOne": "Obama",
    "VotesOne": 6153,
    "IdOne": 1918,
    "FirstTwo": "Mitt",
    "LastTwo": "Romney",
    "VotesTwo": 10159,
    "IdTwo": 893,
    "FirstThree": "Rocky",
    "LastThree": "Anderson",
    "VotesThree": 11,
    "IDThree": 43773,
    "FirstFour": "Jim",
    "LastFour": "Carlson",
    "VotesFour": 29,
    "IdFour": 62588,
    "FirstFive": "Virgil",
    "LastFive": "Goode",
    "VotesFive": 33,
    "IDFive": 713,
    "FirstSix": "James",
    "LastSix": "Harris",
    "VotesSix": 16,
    "IDSix": 3486,
    "FirstSeven": "Gary",
    "LastSeven": "Johnson",
    "VotesSeven": 175,
    "IDSeven": 31708,
    "FirstEight": "Peta",
    "LastEight": "Lindsay",
    "VotesEight": 2,
    "IDEight": 62562,
    "FirstNine": "Jill",
    "LastNine": "Stein",
    "VotesNine": 78,
    "IdNine": 895,
    "": 16662
  },
  {
    "State Postal": "MN",
    "FIPS Code": 27099,
    "County Name": "Mower",
    "TOTAL VOTES CAST": 18471,
    "FirstOne": "Barack",
    "LastOne": "Obama",
    "VotesOne": 11129,
    "IdOne": 1918,
    "FirstTwo": "Mitt",
    "LastTwo": "Romney",
    "VotesTwo": 6938,
    "IdTwo": 893,
    "FirstThree": "Rocky",
    "LastThree": "Anderson",
    "VotesThree": 11,
    "IDThree": 43773,
    "FirstFour": "Jim",
    "LastFour": "Carlson",
    "VotesFour": 40,
    "IdFour": 62588,
    "FirstFive": "Virgil",
    "LastFive": "Goode",
    "VotesFive": 33,
    "IDFive": 713,
    "FirstSix": "James",
    "LastSix": "Harris",
    "VotesSix": 16,
    "IDSix": 3486,
    "FirstSeven": "Gary",
    "LastSeven": "Johnson",
    "VotesSeven": 219,
    "IDSeven": 31708,
    "FirstEight": "Peta",
    "LastEight": "Lindsay",
    "VotesEight": 3,
    "IDEight": 62562,
    "FirstNine": "Jill",
    "LastNine": "Stein",
    "VotesNine": 70,
    "IdNine": 895,
    "": 18471
  },
  {
    "State Postal": "MN",
    "FIPS Code": 27101,
    "County Name": "Murray",
    "TOTAL VOTES CAST": 4754,
    "FirstOne": "Barack",
    "LastOne": "Obama",
    "VotesOne": 2160,
    "IdOne": 1918,
    "FirstTwo": "Mitt",
    "LastTwo": "Romney",
    "VotesTwo": 2504,
    "IdTwo": 893,
    "FirstThree": "Rocky",
    "LastThree": "Anderson",
    "VotesThree": 3,
    "IDThree": 43773,
    "FirstFour": "Jim",
    "LastFour": "Carlson",
    "VotesFour": 16,
    "IdFour": 62588,
    "FirstFive": "Virgil",
    "LastFive": "Goode",
    "VotesFive": 9,
    "IDFive": 713,
    "FirstSix": "James",
    "LastSix": "Harris",
    "VotesSix": 1,
    "IDSix": 3486,
    "FirstSeven": "Gary",
    "LastSeven": "Johnson",
    "VotesSeven": 38,
    "IDSeven": 31708,
    "FirstEight": "Peta",
    "LastEight": "Lindsay",
    "VotesEight": 0,
    "IDEight": 62562,
    "FirstNine": "Jill",
    "LastNine": "Stein",
    "VotesNine": 21,
    "IdNine": 895,
    "": 4754
  },
  {
    "State Postal": "MN",
    "FIPS Code": 27103,
    "County Name": "Nicollet",
    "TOTAL VOTES CAST": 18285,
    "FirstOne": "Barack",
    "LastOne": "Obama",
    "VotesOne": 9652,
    "IdOne": 1918,
    "FirstTwo": "Mitt",
    "LastTwo": "Romney",
    "VotesTwo": 8214,
    "IdTwo": 893,
    "FirstThree": "Rocky",
    "LastThree": "Anderson",
    "VotesThree": 15,
    "IDThree": 43773,
    "FirstFour": "Jim",
    "LastFour": "Carlson",
    "VotesFour": 22,
    "IdFour": 62588,
    "FirstFive": "Virgil",
    "LastFive": "Goode",
    "VotesFive": 27,
    "IDFive": 713,
    "FirstSix": "James",
    "LastSix": "Harris",
    "VotesSix": 13,
    "IDSix": 3486,
    "FirstSeven": "Gary",
    "LastSeven": "Johnson",
    "VotesSeven": 237,
    "IDSeven": 31708,
    "FirstEight": "Peta",
    "LastEight": "Lindsay",
    "VotesEight": 3,
    "IDEight": 62562,
    "FirstNine": "Jill",
    "LastNine": "Stein",
    "VotesNine": 100,
    "IdNine": 895,
    "": 18285
  },
  {
    "State Postal": "MN",
    "FIPS Code": 27105,
    "County Name": "Nobles",
    "TOTAL VOTES CAST": 8493,
    "FirstOne": "Barack",
    "LastOne": "Obama",
    "VotesOne": 3793,
    "IdOne": 1918,
    "FirstTwo": "Mitt",
    "LastTwo": "Romney",
    "VotesTwo": 4581,
    "IdTwo": 893,
    "FirstThree": "Rocky",
    "LastThree": "Anderson",
    "VotesThree": 3,
    "IDThree": 43773,
    "FirstFour": "Jim",
    "LastFour": "Carlson",
    "VotesFour": 14,
    "IdFour": 62588,
    "FirstFive": "Virgil",
    "LastFive": "Goode",
    "VotesFive": 21,
    "IDFive": 713,
    "FirstSix": "James",
    "LastSix": "Harris",
    "VotesSix": 5,
    "IDSix": 3486,
    "FirstSeven": "Gary",
    "LastSeven": "Johnson",
    "VotesSeven": 58,
    "IDSeven": 31708,
    "FirstEight": "Peta",
    "LastEight": "Lindsay",
    "VotesEight": 0,
    "IDEight": 62562,
    "FirstNine": "Jill",
    "LastNine": "Stein",
    "VotesNine": 15,
    "IdNine": 895,
    "": 8493
  },
  {
    "State Postal": "MN",
    "FIPS Code": 27107,
    "County Name": "Norman",
    "TOTAL VOTES CAST": 3199,
    "FirstOne": "Barack",
    "LastOne": "Obama",
    "VotesOne": 1730,
    "IdOne": 1918,
    "FirstTwo": "Mitt",
    "LastTwo": "Romney",
    "VotesTwo": 1384,
    "IdTwo": 893,
    "FirstThree": "Rocky",
    "LastThree": "Anderson",
    "VotesThree": 2,
    "IDThree": 43773,
    "FirstFour": "Jim",
    "LastFour": "Carlson",
    "VotesFour": 11,
    "IdFour": 62588,
    "FirstFive": "Virgil",
    "LastFive": "Goode",
    "VotesFive": 8,
    "IDFive": 713,
    "FirstSix": "James",
    "LastSix": "Harris",
    "VotesSix": 0,
    "IDSix": 3486,
    "FirstSeven": "Gary",
    "LastSeven": "Johnson",
    "VotesSeven": 45,
    "IDSeven": 31708,
    "FirstEight": "Peta",
    "LastEight": "Lindsay",
    "VotesEight": 0,
    "IDEight": 62562,
    "FirstNine": "Jill",
    "LastNine": "Stein",
    "VotesNine": 18,
    "IdNine": 895,
    "": 3199
  },
  {
    "State Postal": "MN",
    "FIPS Code": 27109,
    "County Name": "Olmsted",
    "TOTAL VOTES CAST": 77951,
    "FirstOne": "Barack",
    "LastOne": "Obama",
    "VotesOne": 39338,
    "IdOne": 1918,
    "FirstTwo": "Mitt",
    "LastTwo": "Romney",
    "VotesTwo": 36832,
    "IdTwo": 893,
    "FirstThree": "Rocky",
    "LastThree": "Anderson",
    "VotesThree": 53,
    "IDThree": 43773,
    "FirstFour": "Jim",
    "LastFour": "Carlson",
    "VotesFour": 79,
    "IdFour": 62588,
    "FirstFive": "Virgil",
    "LastFive": "Goode",
    "VotesFive": 104,
    "IDFive": 713,
    "FirstSix": "James",
    "LastSix": "Harris",
    "VotesSix": 25,
    "IDSix": 3486,
    "FirstSeven": "Gary",
    "LastSeven": "Johnson",
    "VotesSeven": 1158,
    "IDSeven": 31708,
    "FirstEight": "Peta",
    "LastEight": "Lindsay",
    "VotesEight": 9,
    "IDEight": 62562,
    "FirstNine": "Jill",
    "LastNine": "Stein",
    "VotesNine": 332,
    "IdNine": 895,
    "": 77951
  },
  {
    "State Postal": "MN",
    "FIPS Code": 27111,
    "County Name": "Otter Tail",
    "TOTAL VOTES CAST": 31562,
    "FirstOne": "Barack",
    "LastOne": "Obama",
    "VotesOne": 12165,
    "IdOne": 1918,
    "FirstTwo": "Mitt",
    "LastTwo": "Romney",
    "VotesTwo": 18860,
    "IdTwo": 893,
    "FirstThree": "Rocky",
    "LastThree": "Anderson",
    "VotesThree": 25,
    "IDThree": 43773,
    "FirstFour": "Jim",
    "LastFour": "Carlson",
    "VotesFour": 32,
    "IdFour": 62588,
    "FirstFive": "Virgil",
    "LastFive": "Goode",
    "VotesFive": 57,
    "IDFive": 713,
    "FirstSix": "James",
    "LastSix": "Harris",
    "VotesSix": 14,
    "IDSix": 3486,
    "FirstSeven": "Gary",
    "LastSeven": "Johnson",
    "VotesSeven": 253,
    "IDSeven": 31708,
    "FirstEight": "Peta",
    "LastEight": "Lindsay",
    "VotesEight": 3,
    "IDEight": 62562,
    "FirstNine": "Jill",
    "LastNine": "Stein",
    "VotesNine": 134,
    "IdNine": 895,
    "": 31562
  },
  {
    "State Postal": "MN",
    "FIPS Code": 27113,
    "County Name": "Pennington",
    "TOTAL VOTES CAST": 6493,
    "FirstOne": "Barack",
    "LastOne": "Obama",
    "VotesOne": 3024,
    "IdOne": 1918,
    "FirstTwo": "Mitt",
    "LastTwo": "Romney",
    "VotesTwo": 3304,
    "IdTwo": 893,
    "FirstThree": "Rocky",
    "LastThree": "Anderson",
    "VotesThree": 0,
    "IDThree": 43773,
    "FirstFour": "Jim",
    "LastFour": "Carlson",
    "VotesFour": 13,
    "IdFour": 62588,
    "FirstFive": "Virgil",
    "LastFive": "Goode",
    "VotesFive": 10,
    "IDFive": 713,
    "FirstSix": "James",
    "LastSix": "Harris",
    "VotesSix": 8,
    "IDSix": 3486,
    "FirstSeven": "Gary",
    "LastSeven": "Johnson",
    "VotesSeven": 100,
    "IDSeven": 31708,
    "FirstEight": "Peta",
    "LastEight": "Lindsay",
    "VotesEight": 2,
    "IDEight": 62562,
    "FirstNine": "Jill",
    "LastNine": "Stein",
    "VotesNine": 30,
    "IdNine": 895,
    "": 6493
  },
  {
    "State Postal": "MN",
    "FIPS Code": 27115,
    "County Name": "Pine",
    "TOTAL VOTES CAST": 13904,
    "FirstOne": "Barack",
    "LastOne": "Obama",
    "VotesOne": 6750,
    "IdOne": 1918,
    "FirstTwo": "Mitt",
    "LastTwo": "Romney",
    "VotesTwo": 6845,
    "IdTwo": 893,
    "FirstThree": "Rocky",
    "LastThree": "Anderson",
    "VotesThree": 7,
    "IDThree": 43773,
    "FirstFour": "Jim",
    "LastFour": "Carlson",
    "VotesFour": 33,
    "IdFour": 62588,
    "FirstFive": "Virgil",
    "LastFive": "Goode",
    "VotesFive": 28,
    "IDFive": 713,
    "FirstSix": "James",
    "LastSix": "Harris",
    "VotesSix": 5,
    "IDSix": 3486,
    "FirstSeven": "Gary",
    "LastSeven": "Johnson",
    "VotesSeven": 162,
    "IDSeven": 31708,
    "FirstEight": "Peta",
    "LastEight": "Lindsay",
    "VotesEight": 2,
    "IDEight": 62562,
    "FirstNine": "Jill",
    "LastNine": "Stein",
    "VotesNine": 64,
    "IdNine": 895,
    "": 13904
  },
  {
    "State Postal": "MN",
    "FIPS Code": 27117,
    "County Name": "Pipestone",
    "TOTAL VOTES CAST": 4637,
    "FirstOne": "Barack",
    "LastOne": "Obama",
    "VotesOne": 1728,
    "IdOne": 1918,
    "FirstTwo": "Mitt",
    "LastTwo": "Romney",
    "VotesTwo": 2828,
    "IdTwo": 893,
    "FirstThree": "Rocky",
    "LastThree": "Anderson",
    "VotesThree": 0,
    "IDThree": 43773,
    "FirstFour": "Jim",
    "LastFour": "Carlson",
    "VotesFour": 5,
    "IdFour": 62588,
    "FirstFive": "Virgil",
    "LastFive": "Goode",
    "VotesFive": 5,
    "IDFive": 713,
    "FirstSix": "James",
    "LastSix": "Harris",
    "VotesSix": 2,
    "IDSix": 3486,
    "FirstSeven": "Gary",
    "LastSeven": "Johnson",
    "VotesSeven": 50,
    "IDSeven": 31708,
    "FirstEight": "Peta",
    "LastEight": "Lindsay",
    "VotesEight": 0,
    "IDEight": 62562,
    "FirstNine": "Jill",
    "LastNine": "Stein",
    "VotesNine": 16,
    "IdNine": 895,
    "": 4637
  },
  {
    "State Postal": "MN",
    "FIPS Code": 27119,
    "County Name": "Polk",
    "TOTAL VOTES CAST": 14644,
    "FirstOne": "Barack",
    "LastOne": "Obama",
    "VotesOne": 6773,
    "IdOne": 1918,
    "FirstTwo": "Mitt",
    "LastTwo": "Romney",
    "VotesTwo": 7615,
    "IdTwo": 893,
    "FirstThree": "Rocky",
    "LastThree": "Anderson",
    "VotesThree": 14,
    "IDThree": 43773,
    "FirstFour": "Jim",
    "LastFour": "Carlson",
    "VotesFour": 15,
    "IdFour": 62588,
    "FirstFive": "Virgil",
    "LastFive": "Goode",
    "VotesFive": 9,
    "IDFive": 713,
    "FirstSix": "James",
    "LastSix": "Harris",
    "VotesSix": 5,
    "IDSix": 3486,
    "FirstSeven": "Gary",
    "LastSeven": "Johnson",
    "VotesSeven": 155,
    "IDSeven": 31708,
    "FirstEight": "Peta",
    "LastEight": "Lindsay",
    "VotesEight": 1,
    "IDEight": 62562,
    "FirstNine": "Jill",
    "LastNine": "Stein",
    "VotesNine": 44,
    "IdNine": 895,
    "": 14644
  },
  {
    "State Postal": "MN",
    "FIPS Code": 27121,
    "County Name": "Pope",
    "TOTAL VOTES CAST": 6224,
    "FirstOne": "Barack",
    "LastOne": "Obama",
    "VotesOne": 2981,
    "IdOne": 1918,
    "FirstTwo": "Mitt",
    "LastTwo": "Romney",
    "VotesTwo": 3142,
    "IdTwo": 893,
    "FirstThree": "Rocky",
    "LastThree": "Anderson",
    "VotesThree": 2,
    "IDThree": 43773,
    "FirstFour": "Jim",
    "LastFour": "Carlson",
    "VotesFour": 8,
    "IdFour": 62588,
    "FirstFive": "Virgil",
    "LastFive": "Goode",
    "VotesFive": 14,
    "IDFive": 713,
    "FirstSix": "James",
    "LastSix": "Harris",
    "VotesSix": 1,
    "IDSix": 3486,
    "FirstSeven": "Gary",
    "LastSeven": "Johnson",
    "VotesSeven": 51,
    "IDSeven": 31708,
    "FirstEight": "Peta",
    "LastEight": "Lindsay",
    "VotesEight": 0,
    "IDEight": 62562,
    "FirstNine": "Jill",
    "LastNine": "Stein",
    "VotesNine": 22,
    "IdNine": 895,
    "": 6224
  },
  {
    "State Postal": "MN",
    "FIPS Code": 27123,
    "County Name": "Ramsey",
    "TOTAL VOTES CAST": 277782,
    "FirstOne": "Barack",
    "LastOne": "Obama",
    "VotesOne": 184936,
    "IdOne": 1918,
    "FirstTwo": "Mitt",
    "LastTwo": "Romney",
    "VotesTwo": 86799,
    "IdTwo": 893,
    "FirstThree": "Rocky",
    "LastThree": "Anderson",
    "VotesThree": 236,
    "IDThree": 43773,
    "FirstFour": "Jim",
    "LastFour": "Carlson",
    "VotesFour": 224,
    "IdFour": 62588,
    "FirstFive": "Virgil",
    "LastFive": "Goode",
    "VotesFive": 244,
    "IDFive": 713,
    "FirstSix": "James",
    "LastSix": "Harris",
    "VotesSix": 119,
    "IDSix": 3486,
    "FirstSeven": "Gary",
    "LastSeven": "Johnson",
    "VotesSeven": 3460,
    "IDSeven": 31708,
    "FirstEight": "Peta",
    "LastEight": "Lindsay",
    "VotesEight": 52,
    "IDEight": 62562,
    "FirstNine": "Jill",
    "LastNine": "Stein",
    "VotesNine": 1611,
    "IdNine": 895,
    "": 277782
  },
  {
    "State Postal": "MN",
    "FIPS Code": 27125,
    "County Name": "Red Lake",
    "TOTAL VOTES CAST": 1963,
    "FirstOne": "Barack",
    "LastOne": "Obama",
    "VotesOne": 928,
    "IdOne": 1918,
    "FirstTwo": "Mitt",
    "LastTwo": "Romney",
    "VotesTwo": 978,
    "IdTwo": 893,
    "FirstThree": "Rocky",
    "LastThree": "Anderson",
    "VotesThree": 3,
    "IDThree": 43773,
    "FirstFour": "Jim",
    "LastFour": "Carlson",
    "VotesFour": 7,
    "IdFour": 62588,
    "FirstFive": "Virgil",
    "LastFive": "Goode",
    "VotesFive": 6,
    "IDFive": 713,
    "FirstSix": "James",
    "LastSix": "Harris",
    "VotesSix": 2,
    "IDSix": 3486,
    "FirstSeven": "Gary",
    "LastSeven": "Johnson",
    "VotesSeven": 24,
    "IDSeven": 31708,
    "FirstEight": "Peta",
    "LastEight": "Lindsay",
    "VotesEight": 2,
    "IDEight": 62562,
    "FirstNine": "Jill",
    "LastNine": "Stein",
    "VotesNine": 10,
    "IdNine": 895,
    "": 1963
  },
  {
    "State Postal": "MN",
    "FIPS Code": 27127,
    "County Name": "Redwood",
    "TOTAL VOTES CAST": 7761,
    "FirstOne": "Barack",
    "LastOne": "Obama",
    "VotesOne": 3008,
    "IdOne": 1918,
    "FirstTwo": "Mitt",
    "LastTwo": "Romney",
    "VotesTwo": 4570,
    "IdTwo": 893,
    "FirstThree": "Rocky",
    "LastThree": "Anderson",
    "VotesThree": 7,
    "IDThree": 43773,
    "FirstFour": "Jim",
    "LastFour": "Carlson",
    "VotesFour": 14,
    "IdFour": 62588,
    "FirstFive": "Virgil",
    "LastFive": "Goode",
    "VotesFive": 32,
    "IDFive": 713,
    "FirstSix": "James",
    "LastSix": "Harris",
    "VotesSix": 4,
    "IDSix": 3486,
    "FirstSeven": "Gary",
    "LastSeven": "Johnson",
    "VotesSeven": 93,
    "IDSeven": 31708,
    "FirstEight": "Peta",
    "LastEight": "Lindsay",
    "VotesEight": 2,
    "IDEight": 62562,
    "FirstNine": "Jill",
    "LastNine": "Stein",
    "VotesNine": 27,
    "IdNine": 895,
    "": 7761
  },
  {
    "State Postal": "MN",
    "FIPS Code": 27129,
    "County Name": "Renville",
    "TOTAL VOTES CAST": 7684,
    "FirstOne": "Barack",
    "LastOne": "Obama",
    "VotesOne": 3394,
    "IdOne": 1918,
    "FirstTwo": "Mitt",
    "LastTwo": "Romney",
    "VotesTwo": 4149,
    "IdTwo": 893,
    "FirstThree": "Rocky",
    "LastThree": "Anderson",
    "VotesThree": 5,
    "IDThree": 43773,
    "FirstFour": "Jim",
    "LastFour": "Carlson",
    "VotesFour": 15,
    "IdFour": 62588,
    "FirstFive": "Virgil",
    "LastFive": "Goode",
    "VotesFive": 18,
    "IDFive": 713,
    "FirstSix": "James",
    "LastSix": "Harris",
    "VotesSix": 6,
    "IDSix": 3486,
    "FirstSeven": "Gary",
    "LastSeven": "Johnson",
    "VotesSeven": 65,
    "IDSeven": 31708,
    "FirstEight": "Peta",
    "LastEight": "Lindsay",
    "VotesEight": 0,
    "IDEight": 62562,
    "FirstNine": "Jill",
    "LastNine": "Stein",
    "VotesNine": 27,
    "IdNine": 895,
    "": 7684
  },
  {
    "State Postal": "MN",
    "FIPS Code": 27131,
    "County Name": "Rice",
    "TOTAL VOTES CAST": 32160,
    "FirstOne": "Barack",
    "LastOne": "Obama",
    "VotesOne": 17054,
    "IdOne": 1918,
    "FirstTwo": "Mitt",
    "LastTwo": "Romney",
    "VotesTwo": 14380,
    "IdTwo": 893,
    "FirstThree": "Rocky",
    "LastThree": "Anderson",
    "VotesThree": 23,
    "IDThree": 43773,
    "FirstFour": "Jim",
    "LastFour": "Carlson",
    "VotesFour": 35,
    "IdFour": 62588,
    "FirstFive": "Virgil",
    "LastFive": "Goode",
    "VotesFive": 48,
    "IDFive": 713,
    "FirstSix": "James",
    "LastSix": "Harris",
    "VotesSix": 12,
    "IDSix": 3486,
    "FirstSeven": "Gary",
    "LastSeven": "Johnson",
    "VotesSeven": 420,
    "IDSeven": 31708,
    "FirstEight": "Peta",
    "LastEight": "Lindsay",
    "VotesEight": 5,
    "IDEight": 62562,
    "FirstNine": "Jill",
    "LastNine": "Stein",
    "VotesNine": 168,
    "IdNine": 895,
    "": 32160
  },
  {
    "State Postal": "MN",
    "FIPS Code": 27133,
    "County Name": "Rock",
    "TOTAL VOTES CAST": 4830,
    "FirstOne": "Barack",
    "LastOne": "Obama",
    "VotesOne": 1945,
    "IdOne": 1918,
    "FirstTwo": "Mitt",
    "LastTwo": "Romney",
    "VotesTwo": 2810,
    "IdTwo": 893,
    "FirstThree": "Rocky",
    "LastThree": "Anderson",
    "VotesThree": 4,
    "IDThree": 43773,
    "FirstFour": "Jim",
    "LastFour": "Carlson",
    "VotesFour": 5,
    "IdFour": 62588,
    "FirstFive": "Virgil",
    "LastFive": "Goode",
    "VotesFive": 7,
    "IDFive": 713,
    "FirstSix": "James",
    "LastSix": "Harris",
    "VotesSix": 2,
    "IDSix": 3486,
    "FirstSeven": "Gary",
    "LastSeven": "Johnson",
    "VotesSeven": 39,
    "IDSeven": 31708,
    "FirstEight": "Peta",
    "LastEight": "Lindsay",
    "VotesEight": 0,
    "IDEight": 62562,
    "FirstNine": "Jill",
    "LastNine": "Stein",
    "VotesNine": 17,
    "IdNine": 895,
    "": 4830
  },
  {
    "State Postal": "MN",
    "FIPS Code": 27135,
    "County Name": "Roseau",
    "TOTAL VOTES CAST": 7330,
    "FirstOne": "Barack",
    "LastOne": "Obama",
    "VotesOne": 2772,
    "IdOne": 1918,
    "FirstTwo": "Mitt",
    "LastTwo": "Romney",
    "VotesTwo": 4409,
    "IdTwo": 893,
    "FirstThree": "Rocky",
    "LastThree": "Anderson",
    "VotesThree": 6,
    "IDThree": 43773,
    "FirstFour": "Jim",
    "LastFour": "Carlson",
    "VotesFour": 12,
    "IdFour": 62588,
    "FirstFive": "Virgil",
    "LastFive": "Goode",
    "VotesFive": 23,
    "IDFive": 713,
    "FirstSix": "James",
    "LastSix": "Harris",
    "VotesSix": 6,
    "IDSix": 3486,
    "FirstSeven": "Gary",
    "LastSeven": "Johnson",
    "VotesSeven": 72,
    "IDSeven": 31708,
    "FirstEight": "Peta",
    "LastEight": "Lindsay",
    "VotesEight": 1,
    "IDEight": 62562,
    "FirstNine": "Jill",
    "LastNine": "Stein",
    "VotesNine": 25,
    "IdNine": 895,
    "": 7330
  },
  {
    "State Postal": "MN",
    "FIPS Code": 27137,
    "County Name": "St. Louis",
    "TOTAL VOTES CAST": 116460,
    "FirstOne": "Barack",
    "LastOne": "Obama",
    "VotesOne": 74177,
    "IdOne": 1918,
    "FirstTwo": "Mitt",
    "LastTwo": "Romney",
    "VotesTwo": 39675,
    "IdTwo": 893,
    "FirstThree": "Rocky",
    "LastThree": "Anderson",
    "VotesThree": 85,
    "IDThree": 43773,
    "FirstFour": "Jim",
    "LastFour": "Carlson",
    "VotesFour": 194,
    "IdFour": 62588,
    "FirstFive": "Virgil",
    "LastFive": "Goode",
    "VotesFive": 193,
    "IDFive": 713,
    "FirstSix": "James",
    "LastSix": "Harris",
    "VotesSix": 32,
    "IDSix": 3486,
    "FirstSeven": "Gary",
    "LastSeven": "Johnson",
    "VotesSeven": 1419,
    "IDSeven": 31708,
    "FirstEight": "Peta",
    "LastEight": "Lindsay",
    "VotesEight": 13,
    "IDEight": 62562,
    "FirstNine": "Jill",
    "LastNine": "Stein",
    "VotesNine": 614,
    "IdNine": 895,
    "": 116460
  },
  {
    "State Postal": "MN",
    "FIPS Code": 27139,
    "County Name": "Scott",
    "TOTAL VOTES CAST": 71411,
    "FirstOne": "Barack",
    "LastOne": "Obama",
    "VotesOne": 29714,
    "IdOne": 1918,
    "FirstTwo": "Mitt",
    "LastTwo": "Romney",
    "VotesTwo": 40321,
    "IdTwo": 893,
    "FirstThree": "Rocky",
    "LastThree": "Anderson",
    "VotesThree": 47,
    "IDThree": 43773,
    "FirstFour": "Jim",
    "LastFour": "Carlson",
    "VotesFour": 61,
    "IdFour": 62588,
    "FirstFive": "Virgil",
    "LastFive": "Goode",
    "VotesFive": 61,
    "IDFive": 713,
    "FirstSix": "James",
    "LastSix": "Harris",
    "VotesSix": 20,
    "IDSix": 3486,
    "FirstSeven": "Gary",
    "LastSeven": "Johnson",
    "VotesSeven": 941,
    "IDSeven": 31708,
    "FirstEight": "Peta",
    "LastEight": "Lindsay",
    "VotesEight": 5,
    "IDEight": 62562,
    "FirstNine": "Jill",
    "LastNine": "Stein",
    "VotesNine": 217,
    "IdNine": 895,
    "": 71411
  },
  {
    "State Postal": "MN",
    "FIPS Code": 27141,
    "County Name": "Sherburne",
    "TOTAL VOTES CAST": 46320,
    "FirstOne": "Barack",
    "LastOne": "Obama",
    "VotesOne": 17597,
    "IdOne": 1918,
    "FirstTwo": "Mitt",
    "LastTwo": "Romney",
    "VotesTwo": 27848,
    "IdTwo": 893,
    "FirstThree": "Rocky",
    "LastThree": "Anderson",
    "VotesThree": 26,
    "IDThree": 43773,
    "FirstFour": "Jim",
    "LastFour": "Carlson",
    "VotesFour": 63,
    "IdFour": 62588,
    "FirstFive": "Virgil",
    "LastFive": "Goode",
    "VotesFive": 61,
    "IDFive": 713,
    "FirstSix": "James",
    "LastSix": "Harris",
    "VotesSix": 13,
    "IDSix": 3486,
    "FirstSeven": "Gary",
    "LastSeven": "Johnson",
    "VotesSeven": 541,
    "IDSeven": 31708,
    "FirstEight": "Peta",
    "LastEight": "Lindsay",
    "VotesEight": 2,
    "IDEight": 62562,
    "FirstNine": "Jill",
    "LastNine": "Stein",
    "VotesNine": 145,
    "IdNine": 895,
    "": 46320
  },
  {
    "State Postal": "MN",
    "FIPS Code": 27143,
    "County Name": "Sibley",
    "TOTAL VOTES CAST": 7785,
    "FirstOne": "Barack",
    "LastOne": "Obama",
    "VotesOne": 2916,
    "IdOne": 1918,
    "FirstTwo": "Mitt",
    "LastTwo": "Romney",
    "VotesTwo": 4693,
    "IdTwo": 893,
    "FirstThree": "Rocky",
    "LastThree": "Anderson",
    "VotesThree": 4,
    "IDThree": 43773,
    "FirstFour": "Jim",
    "LastFour": "Carlson",
    "VotesFour": 11,
    "IdFour": 62588,
    "FirstFive": "Virgil",
    "LastFive": "Goode",
    "VotesFive": 9,
    "IDFive": 713,
    "FirstSix": "James",
    "LastSix": "Harris",
    "VotesSix": 0,
    "IDSix": 3486,
    "FirstSeven": "Gary",
    "LastSeven": "Johnson",
    "VotesSeven": 113,
    "IDSeven": 31708,
    "FirstEight": "Peta",
    "LastEight": "Lindsay",
    "VotesEight": 1,
    "IDEight": 62562,
    "FirstNine": "Jill",
    "LastNine": "Stein",
    "VotesNine": 36,
    "IdNine": 895,
    "": 7785
  },
  {
    "State Postal": "MN",
    "FIPS Code": 27145,
    "County Name": "Stearns",
    "TOTAL VOTES CAST": 78178,
    "FirstOne": "Barack",
    "LastOne": "Obama",
    "VotesOne": 33552,
    "IdOne": 1918,
    "FirstTwo": "Mitt",
    "LastTwo": "Romney",
    "VotesTwo": 43015,
    "IdTwo": 893,
    "FirstThree": "Rocky",
    "LastThree": "Anderson",
    "VotesThree": 48,
    "IDThree": 43773,
    "FirstFour": "Jim",
    "LastFour": "Carlson",
    "VotesFour": 82,
    "IdFour": 62588,
    "FirstFive": "Virgil",
    "LastFive": "Goode",
    "VotesFive": 115,
    "IDFive": 713,
    "FirstSix": "James",
    "LastSix": "Harris",
    "VotesSix": 35,
    "IDSix": 3486,
    "FirstSeven": "Gary",
    "LastSeven": "Johnson",
    "VotesSeven": 955,
    "IDSeven": 31708,
    "FirstEight": "Peta",
    "LastEight": "Lindsay",
    "VotesEight": 11,
    "IDEight": 62562,
    "FirstNine": "Jill",
    "LastNine": "Stein",
    "VotesNine": 338,
    "IdNine": 895,
    "": 78178
  },
  {
    "State Postal": "MN",
    "FIPS Code": 27147,
    "County Name": "Steele",
    "TOTAL VOTES CAST": 19034,
    "FirstOne": "Barack",
    "LastOne": "Obama",
    "VotesOne": 8706,
    "IdOne": 1918,
    "FirstTwo": "Mitt",
    "LastTwo": "Romney",
    "VotesTwo": 9903,
    "IdTwo": 893,
    "FirstThree": "Rocky",
    "LastThree": "Anderson",
    "VotesThree": 15,
    "IDThree": 43773,
    "FirstFour": "Jim",
    "LastFour": "Carlson",
    "VotesFour": 30,
    "IdFour": 62588,
    "FirstFive": "Virgil",
    "LastFive": "Goode",
    "VotesFive": 25,
    "IDFive": 713,
    "FirstSix": "James",
    "LastSix": "Harris",
    "VotesSix": 16,
    "IDSix": 3486,
    "FirstSeven": "Gary",
    "LastSeven": "Johnson",
    "VotesSeven": 254,
    "IDSeven": 31708,
    "FirstEight": "Peta",
    "LastEight": "Lindsay",
    "VotesEight": 2,
    "IDEight": 62562,
    "FirstNine": "Jill",
    "LastNine": "Stein",
    "VotesNine": 75,
    "IdNine": 895,
    "": 19034
  },
  {
    "State Postal": "MN",
    "FIPS Code": 27149,
    "County Name": "Stevens",
    "TOTAL VOTES CAST": 5621,
    "FirstOne": "Barack",
    "LastOne": "Obama",
    "VotesOne": 2742,
    "IdOne": 1918,
    "FirstTwo": "Mitt",
    "LastTwo": "Romney",
    "VotesTwo": 2766,
    "IdTwo": 893,
    "FirstThree": "Rocky",
    "LastThree": "Anderson",
    "VotesThree": 5,
    "IDThree": 43773,
    "FirstFour": "Jim",
    "LastFour": "Carlson",
    "VotesFour": 8,
    "IdFour": 62588,
    "FirstFive": "Virgil",
    "LastFive": "Goode",
    "VotesFive": 8,
    "IDFive": 713,
    "FirstSix": "James",
    "LastSix": "Harris",
    "VotesSix": 4,
    "IDSix": 3486,
    "FirstSeven": "Gary",
    "LastSeven": "Johnson",
    "VotesSeven": 57,
    "IDSeven": 31708,
    "FirstEight": "Peta",
    "LastEight": "Lindsay",
    "VotesEight": 0,
    "IDEight": 62562,
    "FirstNine": "Jill",
    "LastNine": "Stein",
    "VotesNine": 31,
    "IdNine": 895,
    "": 5621
  },
  {
    "State Postal": "MN",
    "FIPS Code": 27151,
    "County Name": "Swift",
    "TOTAL VOTES CAST": 5087,
    "FirstOne": "Barack",
    "LastOne": "Obama",
    "VotesOne": 2751,
    "IdOne": 1918,
    "FirstTwo": "Mitt",
    "LastTwo": "Romney",
    "VotesTwo": 2248,
    "IdTwo": 893,
    "FirstThree": "Rocky",
    "LastThree": "Anderson",
    "VotesThree": 2,
    "IDThree": 43773,
    "FirstFour": "Jim",
    "LastFour": "Carlson",
    "VotesFour": 9,
    "IdFour": 62588,
    "FirstFive": "Virgil",
    "LastFive": "Goode",
    "VotesFive": 5,
    "IDFive": 713,
    "FirstSix": "James",
    "LastSix": "Harris",
    "VotesSix": 2,
    "IDSix": 3486,
    "FirstSeven": "Gary",
    "LastSeven": "Johnson",
    "VotesSeven": 51,
    "IDSeven": 31708,
    "FirstEight": "Peta",
    "LastEight": "Lindsay",
    "VotesEight": 1,
    "IDEight": 62562,
    "FirstNine": "Jill",
    "LastNine": "Stein",
    "VotesNine": 15,
    "IdNine": 895,
    "": 5087
  },
  {
    "State Postal": "MN",
    "FIPS Code": 27153,
    "County Name": "Todd",
    "TOTAL VOTES CAST": 11762,
    "FirstOne": "Barack",
    "LastOne": "Obama",
    "VotesOne": 4819,
    "IdOne": 1918,
    "FirstTwo": "Mitt",
    "LastTwo": "Romney",
    "VotesTwo": 6719,
    "IdTwo": 893,
    "FirstThree": "Rocky",
    "LastThree": "Anderson",
    "VotesThree": 10,
    "IDThree": 43773,
    "FirstFour": "Jim",
    "LastFour": "Carlson",
    "VotesFour": 15,
    "IdFour": 62588,
    "FirstFive": "Virgil",
    "LastFive": "Goode",
    "VotesFive": 29,
    "IDFive": 713,
    "FirstSix": "James",
    "LastSix": "Harris",
    "VotesSix": 2,
    "IDSix": 3486,
    "FirstSeven": "Gary",
    "LastSeven": "Johnson",
    "VotesSeven": 117,
    "IDSeven": 31708,
    "FirstEight": "Peta",
    "LastEight": "Lindsay",
    "VotesEight": 1,
    "IDEight": 62562,
    "FirstNine": "Jill",
    "LastNine": "Stein",
    "VotesNine": 42,
    "IdNine": 895,
    "": 11762
  },
  {
    "State Postal": "MN",
    "FIPS Code": 27155,
    "County Name": "Traverse",
    "TOTAL VOTES CAST": 1840,
    "FirstOne": "Barack",
    "LastOne": "Obama",
    "VotesOne": 942,
    "IdOne": 1918,
    "FirstTwo": "Mitt",
    "LastTwo": "Romney",
    "VotesTwo": 860,
    "IdTwo": 893,
    "FirstThree": "Rocky",
    "LastThree": "Anderson",
    "VotesThree": 3,
    "IDThree": 43773,
    "FirstFour": "Jim",
    "LastFour": "Carlson",
    "VotesFour": 2,
    "IdFour": 62588,
    "FirstFive": "Virgil",
    "LastFive": "Goode",
    "VotesFive": 4,
    "IDFive": 713,
    "FirstSix": "James",
    "LastSix": "Harris",
    "VotesSix": 0,
    "IDSix": 3486,
    "FirstSeven": "Gary",
    "LastSeven": "Johnson",
    "VotesSeven": 21,
    "IDSeven": 31708,
    "FirstEight": "Peta",
    "LastEight": "Lindsay",
    "VotesEight": 0,
    "IDEight": 62562,
    "FirstNine": "Jill",
    "LastNine": "Stein",
    "VotesNine": 7,
    "IdNine": 895,
    "": 1840
  },
  {
    "State Postal": "MN",
    "FIPS Code": 27157,
    "County Name": "Wabasha",
    "TOTAL VOTES CAST": 11722,
    "FirstOne": "Barack",
    "LastOne": "Obama",
    "VotesOne": 5415,
    "IdOne": 1918,
    "FirstTwo": "Mitt",
    "LastTwo": "Romney",
    "VotesTwo": 6049,
    "IdTwo": 893,
    "FirstThree": "Rocky",
    "LastThree": "Anderson",
    "VotesThree": 10,
    "IDThree": 43773,
    "FirstFour": "Jim",
    "LastFour": "Carlson",
    "VotesFour": 18,
    "IdFour": 62588,
    "FirstFive": "Virgil",
    "LastFive": "Goode",
    "VotesFive": 16,
    "IDFive": 713,
    "FirstSix": "James",
    "LastSix": "Harris",
    "VotesSix": 6,
    "IDSix": 3486,
    "FirstSeven": "Gary",
    "LastSeven": "Johnson",
    "VotesSeven": 147,
    "IDSeven": 31708,
    "FirstEight": "Peta",
    "LastEight": "Lindsay",
    "VotesEight": 1,
    "IDEight": 62562,
    "FirstNine": "Jill",
    "LastNine": "Stein",
    "VotesNine": 55,
    "IdNine": 895,
    "": 11722
  },
  {
    "State Postal": "MN",
    "FIPS Code": 27159,
    "County Name": "Wadena",
    "TOTAL VOTES CAST": 6772,
    "FirstOne": "Barack",
    "LastOne": "Obama",
    "VotesOne": 2492,
    "IdOne": 1918,
    "FirstTwo": "Mitt",
    "LastTwo": "Romney",
    "VotesTwo": 4143,
    "IdTwo": 893,
    "FirstThree": "Rocky",
    "LastThree": "Anderson",
    "VotesThree": 1,
    "IDThree": 43773,
    "FirstFour": "Jim",
    "LastFour": "Carlson",
    "VotesFour": 12,
    "IdFour": 62588,
    "FirstFive": "Virgil",
    "LastFive": "Goode",
    "VotesFive": 20,
    "IDFive": 713,
    "FirstSix": "James",
    "LastSix": "Harris",
    "VotesSix": 4,
    "IDSix": 3486,
    "FirstSeven": "Gary",
    "LastSeven": "Johnson",
    "VotesSeven": 65,
    "IDSeven": 31708,
    "FirstEight": "Peta",
    "LastEight": "Lindsay",
    "VotesEight": 1,
    "IDEight": 62562,
    "FirstNine": "Jill",
    "LastNine": "Stein",
    "VotesNine": 30,
    "IdNine": 895,
    "": 6772
  },
  {
    "State Postal": "MN",
    "FIPS Code": 27161,
    "County Name": "Waseca",
    "TOTAL VOTES CAST": 9706,
    "FirstOne": "Barack",
    "LastOne": "Obama",
    "VotesOne": 4370,
    "IdOne": 1918,
    "FirstTwo": "Mitt",
    "LastTwo": "Romney",
    "VotesTwo": 5116,
    "IdTwo": 893,
    "FirstThree": "Rocky",
    "LastThree": "Anderson",
    "VotesThree": 10,
    "IDThree": 43773,
    "FirstFour": "Jim",
    "LastFour": "Carlson",
    "VotesFour": 13,
    "IdFour": 62588,
    "FirstFive": "Virgil",
    "LastFive": "Goode",
    "VotesFive": 16,
    "IDFive": 713,
    "FirstSix": "James",
    "LastSix": "Harris",
    "VotesSix": 8,
    "IDSix": 3486,
    "FirstSeven": "Gary",
    "LastSeven": "Johnson",
    "VotesSeven": 121,
    "IDSeven": 31708,
    "FirstEight": "Peta",
    "LastEight": "Lindsay",
    "VotesEight": 3,
    "IDEight": 62562,
    "FirstNine": "Jill",
    "LastNine": "Stein",
    "VotesNine": 43,
    "IdNine": 895,
    "": 9706
  },
  {
    "State Postal": "MN",
    "FIPS Code": 27163,
    "County Name": "Washington",
    "TOTAL VOTES CAST": 141711,
    "FirstOne": "Barack",
    "LastOne": "Obama",
    "VotesOne": 70203,
    "IdOne": 1918,
    "FirstTwo": "Mitt",
    "LastTwo": "Romney",
    "VotesTwo": 69137,
    "IdTwo": 893,
    "FirstThree": "Rocky",
    "LastThree": "Anderson",
    "VotesThree": 65,
    "IDThree": 43773,
    "FirstFour": "Jim",
    "LastFour": "Carlson",
    "VotesFour": 105,
    "IdFour": 62588,
    "FirstFive": "Virgil",
    "LastFive": "Goode",
    "VotesFive": 120,
    "IDFive": 713,
    "FirstSix": "James",
    "LastSix": "Harris",
    "VotesSix": 29,
    "IDSix": 3486,
    "FirstSeven": "Gary",
    "LastSeven": "Johnson",
    "VotesSeven": 1596,
    "IDSeven": 31708,
    "FirstEight": "Peta",
    "LastEight": "Lindsay",
    "VotesEight": 15,
    "IDEight": 62562,
    "FirstNine": "Jill",
    "LastNine": "Stein",
    "VotesNine": 401,
    "IdNine": 895,
    "": 141711
  },
  {
    "State Postal": "MN",
    "FIPS Code": 27165,
    "County Name": "Watonwan",
    "TOTAL VOTES CAST": 5115,
    "FirstOne": "Barack",
    "LastOne": "Obama",
    "VotesOne": 2494,
    "IdOne": 1918,
    "FirstTwo": "Mitt",
    "LastTwo": "Romney",
    "VotesTwo": 2517,
    "IdTwo": 893,
    "FirstThree": "Rocky",
    "LastThree": "Anderson",
    "VotesThree": 5,
    "IDThree": 43773,
    "FirstFour": "Jim",
    "LastFour": "Carlson",
    "VotesFour": 12,
    "IdFour": 62588,
    "FirstFive": "Virgil",
    "LastFive": "Goode",
    "VotesFive": 13,
    "IDFive": 713,
    "FirstSix": "James",
    "LastSix": "Harris",
    "VotesSix": 3,
    "IDSix": 3486,
    "FirstSeven": "Gary",
    "LastSeven": "Johnson",
    "VotesSeven": 50,
    "IDSeven": 31708,
    "FirstEight": "Peta",
    "LastEight": "Lindsay",
    "VotesEight": 0,
    "IDEight": 62562,
    "FirstNine": "Jill",
    "LastNine": "Stein",
    "VotesNine": 15,
    "IdNine": 895,
    "": 5115
  },
  {
    "State Postal": "MN",
    "FIPS Code": 27167,
    "County Name": "Wilkin",
    "TOTAL VOTES CAST": 3212,
    "FirstOne": "Barack",
    "LastOne": "Obama",
    "VotesOne": 1258,
    "IdOne": 1918,
    "FirstTwo": "Mitt",
    "LastTwo": "Romney",
    "VotesTwo": 1884,
    "IdTwo": 893,
    "FirstThree": "Rocky",
    "LastThree": "Anderson",
    "VotesThree": 0,
    "IDThree": 43773,
    "FirstFour": "Jim",
    "LastFour": "Carlson",
    "VotesFour": 5,
    "IdFour": 62588,
    "FirstFive": "Virgil",
    "LastFive": "Goode",
    "VotesFive": 5,
    "IDFive": 713,
    "FirstSix": "James",
    "LastSix": "Harris",
    "VotesSix": 2,
    "IDSix": 3486,
    "FirstSeven": "Gary",
    "LastSeven": "Johnson",
    "VotesSeven": 45,
    "IDSeven": 31708,
    "FirstEight": "Peta",
    "LastEight": "Lindsay",
    "VotesEight": 1,
    "IDEight": 62562,
    "FirstNine": "Jill",
    "LastNine": "Stein",
    "VotesNine": 10,
    "IdNine": 895,
    "": 3212
  },
  {
    "State Postal": "MN",
    "FIPS Code": 27169,
    "County Name": "Winona",
    "TOTAL VOTES CAST": 27103,
    "FirstOne": "Barack",
    "LastOne": "Obama",
    "VotesOne": 14980,
    "IdOne": 1918,
    "FirstTwo": "Mitt",
    "LastTwo": "Romney",
    "VotesTwo": 11480,
    "IdTwo": 893,
    "FirstThree": "Rocky",
    "LastThree": "Anderson",
    "VotesThree": 23,
    "IDThree": 43773,
    "FirstFour": "Jim",
    "LastFour": "Carlson",
    "VotesFour": 26,
    "IdFour": 62588,
    "FirstFive": "Virgil",
    "LastFive": "Goode",
    "VotesFive": 53,
    "IDFive": 713,
    "FirstSix": "James",
    "LastSix": "Harris",
    "VotesSix": 10,
    "IDSix": 3486,
    "FirstSeven": "Gary",
    "LastSeven": "Johnson",
    "VotesSeven": 391,
    "IDSeven": 31708,
    "FirstEight": "Peta",
    "LastEight": "Lindsay",
    "VotesEight": 4,
    "IDEight": 62562,
    "FirstNine": "Jill",
    "LastNine": "Stein",
    "VotesNine": 125,
    "IdNine": 895,
    "": 27103
  },
  {
    "State Postal": "MN",
    "FIPS Code": 27171,
    "County Name": "Wright",
    "TOTAL VOTES CAST": 69550,
    "FirstOne": "Barack",
    "LastOne": "Obama",
    "VotesOne": 26584,
    "IdOne": 1918,
    "FirstTwo": "Mitt",
    "LastTwo": "Romney",
    "VotesTwo": 41460,
    "IdTwo": 893,
    "FirstThree": "Rocky",
    "LastThree": "Anderson",
    "VotesThree": 63,
    "IDThree": 43773,
    "FirstFour": "Jim",
    "LastFour": "Carlson",
    "VotesFour": 105,
    "IdFour": 62588,
    "FirstFive": "Virgil",
    "LastFive": "Goode",
    "VotesFive": 107,
    "IDFive": 713,
    "FirstSix": "James",
    "LastSix": "Harris",
    "VotesSix": 35,
    "IDSix": 3486,
    "FirstSeven": "Gary",
    "LastSeven": "Johnson",
    "VotesSeven": 879,
    "IDSeven": 31708,
    "FirstEight": "Peta",
    "LastEight": "Lindsay",
    "VotesEight": 27,
    "IDEight": 62562,
    "FirstNine": "Jill",
    "LastNine": "Stein",
    "VotesNine": 243,
    "IdNine": 895,
    "": 69550
  },
  {
    "State Postal": "MN",
    "FIPS Code": 27173,
    "County Name": "Yellow Medicine",
    "TOTAL VOTES CAST": 5397,
    "FirstOne": "Barack",
    "LastOne": "Obama",
    "VotesOne": 2465,
    "IdOne": 1918,
    "FirstTwo": "Mitt",
    "LastTwo": "Romney",
    "VotesTwo": 2806,
    "IdTwo": 893,
    "FirstThree": "Rocky",
    "LastThree": "Anderson",
    "VotesThree": 7,
    "IDThree": 43773,
    "FirstFour": "Jim",
    "LastFour": "Carlson",
    "VotesFour": 8,
    "IdFour": 62588,
    "FirstFive": "Virgil",
    "LastFive": "Goode",
    "VotesFive": 12,
    "IDFive": 713,
    "FirstSix": "James",
    "LastSix": "Harris",
    "VotesSix": 3,
    "IDSix": 3486,
    "FirstSeven": "Gary",
    "LastSeven": "Johnson",
    "VotesSeven": 68,
    "IDSeven": 31708,
    "FirstEight": "Peta",
    "LastEight": "Lindsay",
    "VotesEight": 2,
    "IDEight": 62562,
    "FirstNine": "Jill",
    "LastNine": "Stein",
    "VotesNine": 23,
    "IdNine": 895,
    "": 5397
  }
]