[{"County Name":"Washington","Obama#":1750848,"McCain#":1229216,"Nader#":29489,"Barr#":12728,"Baldwin#":9432,"Total":3057054,"FIPS Code":0},
{"County Name":"Adams","Obama#":1346,"McCain#":2822,"Other#":73,"Total":4241,"FIPS Code":53001},
{"County Name":"Asotin","Obama#":4114,"McCain#":5407,"Other#":190,"Total":9711,"FIPS Code":53003},
{"County Name":"Benton","Obama#":23366,"McCain#":40244,"Other#":1087,"Total":64697,"FIPS Code":53005},
{"County Name":"Chelan","Obama#":13678,"McCain#":17484,"Other#":567,"Total":31729,"FIPS Code":53007},
{"County Name":"Clallam","Obama#":17512,"McCain#":15978,"Other#":695,"Total":34185,"FIPS Code":53009},
{"County Name":"Clark","Obama#":93541,"McCain#":82631,"Other#":3117,"Total":179289,"FIPS Code":53011},
{"County Name":"Columbia","Obama#":667,"McCain#":1447,"Other#":41,"Total":2155,"FIPS Code":53013},
{"County Name":"Cowlitz","Obama#":18944,"McCain#":13969,"Other#":745,"Total":33658,"FIPS Code":53015},
{"County Name":"Douglas","Obama#":4631,"McCain#":7048,"Other#":187,"Total":11866,"FIPS Code":53017},
{"County Name":"Ferry","Obama#":1386,"McCain#":1817,"Other#":103,"Total":3306,"FIPS Code":53019},
{"County Name":"Franklin","Obama#":6536,"McCain#":10787,"Other#":258,"Total":17581,"FIPS Code":53021},
{"County Name":"Garfield","Obama#":384,"McCain#":966,"Other#":20,"Total":1370,"FIPS Code":53023},
{"County Name":"Grant","Obama#":9364,"McCain#":16756,"Other#":664,"Total":26784,"FIPS Code":53025},
{"County Name":"Grays Harbor","Obama#":15759,"McCain#":11614,"Other#":699,"Total":28072,"FIPS Code":53027},
{"County Name":"Island","Obama#":21688,"McCain#":19070,"Other#":661,"Total":41419,"FIPS Code":53029},
{"County Name":"Jefferson","Obama#":12914,"McCain#":6195,"Other#":392,"Total":19501,"FIPS Code":53031},
{"County Name":"King","Obama#":545329,"McCain#":217589,"Other#":11218,"Total":774136,"FIPS Code":53033},
{"County Name":"Kitsap","Obama#":61255,"McCain#":47456,"Other#":2043,"Total":110754,"FIPS Code":53035},
{"County Name":"Kittitas","Obama#":7887,"McCain#":9320,"Other#":362,"Total":17569,"FIPS Code":53037},
{"County Name":"Klickitat","Obama#":4871,"McCain#":4868,"Other#":249,"Total":9988,"FIPS Code":53039},
{"County Name":"Lewis","Obama#":11719,"McCain#":17293,"Other#":651,"Total":29663,"FIPS Code":53041},
{"County Name":"Lincoln","Obama#":2024,"McCain#":3794,"Other#":142,"Total":5960,"FIPS Code":53043},
{"County Name":"Mason","Obama#":14934,"McCain#":12512,"Other#":650,"Total":28096,"FIPS Code":53045},
{"County Name":"Okanogan","Obama#":6163,"McCain#":6942,"Other#":344,"Total":13449,"FIPS Code":53047},
{"County Name":"Pacific","Obama#":6066,"McCain#":4531,"Other#":285,"Total":10882,"FIPS Code":53049},
{"County Name":"Pend Oreille","Obama#":2546,"McCain#":3704,"Other#":271,"Total":6521,"FIPS Code":53051},
{"County Name":"Pierce","Obama#":143491,"McCain#":111851,"Other#":4581,"Total":259923,"FIPS Code":53053},
{"County Name":"San Juan","Obama#":7172,"McCain#":2889,"Other#":186,"Total":10247,"FIPS Code":53055},
{"County Name":"Skagit","Obama#":28145,"McCain#":23031,"Other#":1023,"Total":52199,"FIPS Code":53057},
{"County Name":"Skamania","Obama#":2797,"McCain#":2513,"Other#":148,"Total":5458,"FIPS Code":53059},
{"County Name":"Snohomish","Obama#":177471,"McCain#":120064,"Other#":5850,"Total":303385,"FIPS Code":53061},
{"County Name":"Spokane","Obama#":102164,"McCain#":105059,"Other#":5183,"Total":212406,"FIPS Code":53063},
{"County Name":"Stevens","Obama#":6386,"McCain#":9308,"Other#":448,"Total":16142,"FIPS Code":53065},
{"County Name":"Thurston","Obama#":69999,"McCain#":44565,"Other#":2170,"Total":116734,"FIPS Code":53067},
{"County Name":"Wahkiakum","Obama#":1112,"McCain#":1100,"Other#":68,"Total":2280,"FIPS Code":53069},
{"County Name":"Walla Walla","Obama#":7539,"McCain#":10632,"Other#":314,"Total":18485,"FIPS Code":53071},
{"County Name":"Whatcom","Obama#":53313,"McCain#":36635,"Other#":1635,"Total":91583,"FIPS Code":53073},
{"County Name":"Whitman","Obama#":6935,"McCain#":6408,"Other#":303,"Total":13646,"FIPS Code":53075},
{"County Name":"Yakima","Obama#":32484,"McCain#":40877,"Other#":1279,"Total":74640,"FIPS Code":53077}]